Workbook
Name saless: #REF!
Name Slicer_Region: #N/A

Sheet Supplier
A1: Supplier_ID | B1: Supplier_Name | C1: Contact_Person | D1: Phone | E1: Email | F1: City | G1: Lead_Time_Days | H1: Rating | I1: Status
A2: SUP001 | B2: Anna Agro Pvt Ltd | C2: Madhavan Rao | D2: 9826600539 | E2: madhavan.anna@agromail.com | F2: Salem | G2: 4 | H2: 4.3 | I2: Active
A3: SUP002 | B3: Palani Suppliers Pvt Ltd | C3: Kamala Subramaniam | D3: 9349817734 | E3: kamala.palani@suppliersmail.com | F3: Coimbatore | G3: 2 | H3: 2.7 | I3: Active
A4: SUP003 | B4: Saravana Beverages Pvt Ltd | C4: Hari Mudaliar | D4: 9732719211 | E4: hari.saravana@beveragesmail.com | F4: Kochi | G4: 8 | H4: 3.1 | I4: Active
A5: SUP004 | B5: Coastal Household Products Pvt Ltd | C5: Aishwarya Naicker | D5: 9398362082 | E5: aishwarya.coastal@householdmail.com | F5: Madurai | G5: 13 | H5: 3.6 | I5: Active
A6: SUP005 | B6: Vel Traders Pvt Ltd | C6: Padma Raj | D6: 9469319644 | E6: padma.vel@bizcom | F6: Chennai | G6: 8 | H6: 2.7 | I6: Active
A7: SUP006 | B7: Kovai Distributors Pvt Ltd | C7: Vasanthi Venkataraman | D7: 9506448196 | E7: vasanthi.kovai@distributorsmail.com | F7: Kochi | G7: 45 | H7: 4.9 | I7: Active
A8: SUP007 | B8: Om Fresh Produce Pvt Ltd | C8: Raghav Prabhu | D8: 9174684276 | E8: raghav.om@freshmail.com | F8: Tiruppur | G8: 11 | H8: 3 | I8: Active
A9: SUP008 | B9: Sree Snacks Co Pvt Ltd | C9: Naveen Devi | D9: 9398471886 | E9: naveen.sree@snacksmail.com | F9: Salem | G9: 15 | H9: 2.8 | I9: Active
A10: SUP009 | B10: Ganesh Snacks Co Pvt Ltd | C10: Chitra Gupta | D10: 9853573823 | E10: chitra.ganesh@snacksmail.com | F10: Tiruppur | G10: 5 | H10: 4.2 | I10: Active
A11: SUP010 | B11: Bharat Snacks Co Pvt Ltd | C11: Raghav Pillai | D11: 9596348124 | E11: raghav.bharat@snacksmail.com | F11: Kochi | G11: 13 | H11: 3.1 | I11: Active
A12: SUP011 | B12: Malabar Distributors Pvt Ltd | C12: Nandhini Mudaliar | D12: 9924970419 | E12: nandhini.malabar@distributorsmail.com | F12: Kochi | G12: 5 | H12: 4.2 | I12: Active
A13: SUP012 | B13: Tirupati Foods Pvt Ltd | C13: Karthik Naicker | D13: 9326541099 | E13: karthik.tirupati@foodsmail.com | F13: Tiruppur | G13: 8 | H13: 3.2 | I13: Active
... A86: SUP085 | B86: Anna Traders Pvt Ltd | C86: Ezhil Menon | D86: 9707665448 | E86: ezhil.anna@tradersmail.com | F86: Hyderabad | G86: 14 | H86: 2.8 | I86: Active

Sheet Store
A1: Store_ID | B1: Store_Name | C1: Manager | D1: Region | E1: City | F1: State | G1: Store_Type | H1: Opening_Date | I1: Monthly_Target | J1: Status
A2: STR001 | B2: FreshMart Madurai Crossing | C2: Sudha Naicker | D2: South | E2: Madurai | F2: Tamil Nadu | G2: Supermarket | H2: 42147 | I2: 1921769 | J2: Active
A3: STR002 | B3: FreshMart Tiruppur Bypass | C3: Manoj Nair | D3: South | E3: Tiruppur | F3: Tamil Nadu | G3: Convenience | H3: 42633 | I3: 591044 | J3: Active
A4: STR003 | B4: FreshMart Tiruppur Square | C4: Suresh Nathan | D4: South | E4: Tiruppur | F4: Tamil Nadu | G4: Express | H4: 44173 | I4: 890380 | J4: Active
A5: STR004 | B5: FreshMart Erode Plaza | C5: Prakash Kumar | D5: South | E5: Erode | F5: Tamil Nadu | G5: Convenience | H5: 44049 | I5: 584869 | J5: Active
A6: STR005 | B6: FreshMart Chennai Crossing | C6: Lokesh Mudaliar | D6: South | E6: Chennai | F6: Tamil Nadu | G6: Express | H6: 42883 | I6: 983603 | J6: Active
A7: STR006 | B7: FreshMart Mysuru Junction | C7: Senthil Sekar | D7: South | E7: Mysuru | F7: Karnataka | G7: Supermarket | H7: 43856 | I7: 2561982 | J7: Active
A8: STR007 | B8: FreshMart Mysuru Towers | C8: Sudha Sekar | D8: South | E8: Mysuru | F8: Karnataka | G8: Express | H8: 44740 | I8: 988505 | J8: Active
A9: STR008 | B9: FreshMart Kochi Plaza | C9: Malathi Sekar | D9: South | E9: Kochi | F9: Kerala | G9: Supermarket | H9: 44920 | I9: 2481146 | J9: Active
A10: STR009 | B10: FreshMart Kochi Square | C10: Hari Naicker | D10: South | E10: Kochi | F10: Kerala | G10: Convenience | H10: 42974 | I10: 429599 | J10: Active
A11: STR010 | B11: FreshMart Kochi Colony | C11: Bhuvana Naicker | D11: South | E11: Kochi | F11: Kerala | G11: Hypermarket | H11: 42536 | I11: 3928553 | J11: Active
A12: STR011 | B12: FreshMart Bengaluru Enclave | C12: Vasanthi Chandran | D12: South | E12: Bengaluru | F12: Karnataka | G12: Convenience | H12: 43687 | I12: 569084 | J12: Active
A13: STR012 | B13: FreshMart Chennai Junction | C13: Pandi Varma | D13: South | E13: Chennai | F13: Tamil Nadu | G13: Convenience | H13: 43848 | I13: 544019 | J13: Active
... A181: STR180 | B181: FreshMart Guwahati Extension | C181: Suresh Naidu | D181: East | E181: Guwahati | F181: Assam | G181: Hypermarket | H181: 44575 | I181: 4606432 | J181: Active

Sheet Products
A1: Product_ID | B1: Product_Name | C1: Category | D1: Subcategory | E1: Brand | F1: Cost_Price | G1: Selling_Price | H1: Supplier_ID | I1: Season | J1: Status
A2: PRD001 | B2: Local Bakers Buns 1kg | C2: Bakery | D2: Buns | E2: Local Bakers | F2: 184.74 | G2: 299.73 | H2: SUP059 | I2: Summer | J2: Active
A3: PRD002 | B3: Britannia Buns Pack | C3: Bakery | D3: Buns | E3: Britannia | F3: 254.05 | G3: 440.5 | H3: SUP062 | I3: Monsoon | J3: Active
A4: PRD003 | B4: Harvest Gold Buns Combo | C4: Bakery | D4: Buns | E4: Harvest Gold | F4: 343.65 | G4: 589.75 | H4: SUP012 | I4: Winter | J4: Active
A5: PRD004 | B5: Britannia Buns 2kg | C5: Bakery | D5: Buns | E5: Britannia | F5: 236.54 | G5: 398.25 | H5: SUP044 | I5: All Season | J5: Active
A6: PRD005 | B6: Amul Paneer 250ml | C6: Bakery | D6: Buns | E6: Harvest Gold | F6: 205.27 | G6: 332.74 | H6: SUP034 | I6: Winter | J6: Active
A7: PRD006 | B7: Harvest Gold Cookies 500g | C7: Bakery | D7: Cookies | E7: Harvest Gold | F7: 216.32 | G7: 343.56 | H7: SUP031 | I7: Monsoon | J7: Active
A8: PRD007 | B8: Britannia Buns 2kg v2 | C8: Bakery | D8: Buns | E8: Britannia | F8: 265.44 | G8: 437.49 | H8: SUP003 | I8: All Season | J8: Active
A9: PRD008 | B9: Britannia Cookies 200g | C9: Bakery | D9: Cookies | E9: Britannia | F9: 282.88 | G9: 455.79 | H9: SUP075 | I9: Winter | J9: Active
A10: PRD009 | B10: Harvest Gold Buns 200g | C10: Bakery | D10: Buns | E10: Harvest Gold | F10: 398.72 | G10: 661.91 | H10: SUP046 | I10: Monsoon | J10: Active
A11: PRD010 | B11: Harvest Gold Cookies Pack | C11: Bakery | D11: Cookies | E11: Harvest Gold | F11: 107.6 | G11: 182.3 | H11: SUP041 | I11: All Season | J11: Active
A12: PRD011 | B12: Britannia Rusk 1L | C12: Bakery | D12: Rusk | E12: Britannia | F12: 102.23 | G12: 168.36 | H12: SUP076 | I12: Festive | J12: Active
A13: PRD012 | B13: Harvest Gold Rusk 1kg | C13: Bakery | D13: Rusk | E13: Harvest Gold | F13: 336.4 | G13: 541.35 | H13: SUP047 | I13: Summer | J13: Active
... A151: PRD150 | B151: Lizol Toilet Cleaner 200g v2 | C151: Cleaning | D151: Toilet Cleaner | E151: Lizol | F151: 158.06 | G151: 214.04 | H151: SUP021 | I151: All Season | J151: Active

Sheet Employee
A1: Employee_ID | B1: Employee_Name | C1: Gender | D1: Department | E1: Salary | F1: Joining_Date | G1: Store_ID | H1: Employment_Status
A2: EMP0332 | B2: Udhay Gounder | C2: Male | D2: Cashier | E2: 14073 | F2: 42542 | G2: STR149 | H2: Active
A3: EMP0340 | B3: Nithya Subramaniam | C3: Female | D3: Cashier | E3: 14174 | F3: 45193 | G3: STR097 | H3: Active
A4: EMP0157 | B4: Elango Velan | C4: Male | D4: Cashier | E4: 14183 | F4: 43368 | G4: STR012 | H4: Active
A5: EMP0213 | B5: Venkat Varma | C5: Male | D5: Cashier | E5: 14562 | F5: 42739 | G5: STR141 | H5: Active
A6: EMP0319 | B6: Harini Kumar | C6: Female | D6: Cashier | E6: 14584 | F6: 44594 | G6: STR121 | H6: Active
A7: EMP0263 | B7: Vani Nair | C7: Female | D7: Cashier | E7: 14788 | F7: 44212 | G7: STR086 | H7: Active
A8: EMP0018 | B8: Chandran Kumar | C8: Male | D8: Cashier | E8: 14882 | F8: 45471 | G8: STR107 | H8: Active
A9: EMP0058 | B9: Senthil Raj | C9: Male | D9: Cashier | E9: 14977 | F9: 43915 | G9: STR011 | H9: Active
A10: EMP0321 | B10: Sundar Velan | C10: Male | D10: Cashier | E10: 14999 | F10: 45516 | G10: STR064 | H10: Active
A11: EMP0121 | B11: Nithya Selvam | C11: Female | D11: Cashier | E11: 15100 | F11: 45153 | G11: STR085 | H11: Active
A12: EMP0029 | B12: Vasanthi Menon | C12: Female | D12: Cashier | E12: 15131 | F12: 44060 | G12: STR155 | H12: Active
A13: EMP0125 | B13: Nandhini Chettiar | C13: Female | D13: Cashier | E13: 15146 | F13: 46020 | G13: STR138 | H13: Active
... A351: EMP0047 | B351: Sundar Gounder | C351: Male | D351: Store Manager | E351: 67135 | F351: 45398 | G351: STR144 | H351: Active

Sheet Customer
A1: Customer_ID | B1: Customer_Name | C1: Gender | D1: DOB | E1: Phone | F1: Email | G1: City | H1: State | I1: Region | J1: Membership | K1: Registration_Date
A2: CUST0001 | B2: Revathi Balan | C2: Female | D2: 31272 | E2: 9204528821 | F2: revathi1@gmail.com | G2: Coimbatore | H2: Tamil Nadu | I2: South | J2: Bronze | K2: 44659
A3: CUST0002 | B3: Eswari Murugan | C3: Female | D3: 21939 | E3: 9362238769 | F3: eswari2@gmail.com | G3: Tiruppur | H3: Tamil Nadu | I3: South | J3: Silver | K3: 45809
A4: CUST0003 | B4: Banu Balan | C4: Female | D4: 22236 | E4: 9222912620 | F4: banu3@gmail.com | G4: Erode | H4: Tamil Nadu | I4: South | J4: Bronze | K4: 44349
A5: CUST0004 | B5: Naveen Sharma | C5: Male | D5: 21314 | E5: 9806272779 | F5: naveen4@gmail.com | G5: Coimbatore | H5: Tamil Nadu | I5: South | J5: Silver | K5: 44988
A6: CUST0005 | B6: Pandi Raj | C6: Male | D6: 35481 | E6: 9123876200 | F6: pandi5@gmail.com | G6: Guwahati | H6: Assam | I6: East | J6: Silver | K6: 45509
A7: CUST0006 | B7: Thiru Devi | C7: Male | D7: 38850 | E7: 9967934041 | F7: thiru6@gmail.com | G7: Kanpur | H7: Uttar Pradesh | I7: North | J7: Silver | K7: 43501
A8: CUST0007 | B8: Senthil Pillai | C8: Male | D8: 36564 | E8: 9464577685 | F8: senthil7@gmail.com | G8: Salem | H8: Tamil Nadu | I8: South | J8: Silver | K8: 45834
A9: CUST0008 | B9: Eswari Raj | C9: Female | D9: 34376 | E9: 9633597839 | F9: eswari8@gmail.com | G9: Erode | H9: Tamil Nadu | I9: South | J9: Silver | K9: 43927
A10: CUST0009 | B10: Mani Nair | C10: Male | D10: 37648 | E10: 9408545686 | F10: mani9@gmail.com | G10: Chennai | H10: Tamil Nadu | I10: South | J10: Bronze | K10: 43977
A11: CUST0010 | B11: Tara Achari | C11: Female | D11: 33263 | E11: 9770629385 | F11: tara10@gmail.com | G11: Erode | H11: Tamil Nadu | I11: South | J11: Bronze | K11: 44026
A12: CUST0011 | B12: Prasath Mudaliar | C12: Male | D12: 39036 | E12: 9735509839 | F12: prasath11@gmail.com | G12: Chennai | H12: Tamil Nadu | I12: South | J12: Bronze | K12: 43489
A13: CUST0012 | B13: Meena Gupta | C13: Female | D13: 37491 | E13: 9558601461 | F13: meena12@gmail.com | G13: Chennai | H13: Tamil Nadu | I13: South | J13: Bronze | K13: 45047
... A293: CUST0292 | B293: Nirmala Venkataraman | C293: Female | D293: 25491 | E293: 9322664095 | F293: nirmala292@gmail.com | G293: Tiruppur | H293: Tamil Nadu | I293: South | J293: Silver | K293: 44136
A294: CUST0293 | B294: Suresh Chandran | C294: Male | D294: 35225 | E294: 9468999657 | F294: suresh293@gmail.com | G294: Mysuru | H294: Karnataka | J294: Gold | K294: 44662
A295: CUST0294 | B295: Deepak Venkataraman | C295: Male | D295: 20441 | E295: 9223139628 | F295: deepak294@gmail.com | G295: Salem | H295: Tamil Nadu | I295: South | J295: Silver | K295: 44127
A296: CUST0295 | B296: Latha Gounder | C296: Female | D296: 35302 | E296: 9595378308 | F296: latha295@gmail.com | G296: Madurai | H296: Tamil Nadu | I296: South | J296: Silver | K296: 45086
A297: CUST0296 | B297: Uma Pandian | C297: Female | D297: 34433 | E297: 9605504475 | F297: uma296@gmail.com | G297: Kochi | H297: Kerala | I297: South | J297: Bronze | K297: 43675
A298: CUST0297 | B298: Nithya Sharma | C298: Female | D298: 20681 | E298: 9207927292 | F298: nithya297@gmail.com | G298: Madurai | H298: Tamil Nadu | I298: South | J298: Gold | K298: 45587
A299: CUST0298 | B299: Divya Naicker | C299: Female | D299: 32897 | E299: 9183306581 | F299: divya298@gmail.com | G299: Chennai | H299: Tamil Nadu | I299: South | J299: Silver | K299: 43790
A300: CUST0299 | B300: Chandran Krishnan | C300: Male | D300: 25119 | E300: 9484492979 | F300: chandran299@gmail.com | G300: Coimbatore | H300: Tamil Nadu | I300: South | J300: Bronze | K300: 44905
A301: CUST0300 | B301: Indira Prabhu | C301: Female | D301: 37532 | E301: 9574656314 | F301: indira300@gmail.com | G301: Coimbatore | H301: Tamil Nadu | I301: South | J301: Bronze | K301: 43986
A302: CUST0301 | B302: Dinesh Chandran | C302: Male | D302: 23458 | E302: 9841254136 | F302: dinesh301@gmail.com | G302: Kochi | H302: Kerala | I302: South | J302: Bronze | K302: 44700
A303: CUST0302 | B303: Rajesh Reddy | C303: Male | D303: 21684 | E303: 9923682643 | F303: rajesh302@gmail.com | G303: Coimbatore | H303: Tamil Nadu | I303: South | J303: Bronze | K303: 44646
A304: CUST0303 | B304: Kamala Subramaniam | C304: Female | D304: 27906 | E304: 9198125433 | F304: kamala303@gmail.com | G304: Salem | H304: Tamil Nadu | I304: South | J304: Silver | K304: 43920
A305: CUST0304 | B305: Missing Customer Name | C305: Female | D305: 31136 | E305: 9830100976 | F305: yamuna304@gmail.com | G305: Coimbatore | H305: Tamil Nadu | I305: South | J305: Bronze | K305: 43888
A306: CUST0305 | B306: Hemalatha Mudaliar | C306: Female | D306: 23255 | E306: 9280262874 | F306: hemalatha305@gmail.com | G306: Salem | H306: Tamil Nadu | I306: South | J306: Bronze | K306: 45821
... A446: CUST0445 | B446: Anjali Kumar | C446: Female | D446: 20380 | E446: 9562572075 | F446: anjali445@gmail.com | G446: Madurai | H446: Tamil Nadu | I446: South | J446: Silver | K446: 43516
A447: CUST0446 | B447: Ramesh Sharma | C447: Male | D447: 25126 | E447: 9232975024 | F447: ramesh446@gmail.com | G447: Chennai | H447: Tamil Nadu | J447: Silver | K447: 44783
A448: CUST0447 | B448: Harini Krishnan | C448: Female | D448: 28286 | E448: 9605408862 | F448: harini447@gmail.com | G448: Pune | H448: Maharashtra | I448: West | J448: Bronze | K448: 44027
A449: CUST0448 | B449: Sanjay Achari | C449: Male | D449: 26059 | E449: 9971388578 | F449: sanjay448@gmail.com | G449: Erode | H449: Tamil Nadu | I449: South | J449: Silver | K449: 45298
A450: CUST0449 | B450: Sudha Sekar | C450: Female | D450: 34486 | E450: 9250188999 | F450: sudha449@gmail.com | G450: Mysuru | H450: Karnataka | I450: South | J450: Bronze | K450: 43763
A451: CUST0450 | B451: Bhavani Chettiar | C451: Female | D451: 26593 | E451: 9303546093 | F451: bhavani450@gmail.com | G451: Bengaluru | H451: Karnataka | I451: South | J451: Gold | K451: 43554
A452: CUST0451 | B452: Divya Nair | C452: Female | D452: 30943 | E452: 9272134233 | F452: divya451@gmail.com | G452: Madurai | H452: Tamil Nadu | I452: South | J452: Silver | K452: 43230
A453: CUST0452 | B453: Dhanya Varma | C453: Female | D453: 28799 | E453: 9552147658 | F453: dhanya452@gmail.com | G453: Mysuru | H453: Karnataka | I453: South | J453: Bronze | K453: 43587
A454: CUST0453 | B454: Prasath Nair | C454: Male | D454: 24265 | E454: 9906476640 | F454: prasath453@gmail.com | G454: Mysuru | H454: Karnataka | I454: South | J454: Bronze | K454: 44431
A455: CUST0454 | B455: Raghav Nair | C455: Male | D455: 32831 | E455: 9217824679 | F455: raghav454@gmail.com | G455: Bengaluru | H455: Karnataka | I455: South | J455: Silver | K455: 43639
A456: CUST0455 | B456: Nithya Venkataraman | C456: Female | D456: 36474 | E456: 9923973312 | F456: nithya455@gmail.com | G456: Pune | H456: Maharashtra | I456: West | J456: Gold | K456: 43156
A457: CUST0456 | B457: Kamala Devi | C457: Female | D457: 31301 | E457: 9741117091 | F457: kamala456@gmail.com | G457: Coimbatore | H457: Tamil Nadu | I457: South | J457: Bronze | K457: 44860
A458: CUST0457 | B458: Nithya Raj | C458: Female | D458: 29337 | E458: 9188707067 | F458: nithya457@gmail.com | G458: Bengaluru | H458: Karnataka | I458: South | J458: Silver | K458: 45091
A459: CUST0458 | B459: Prasath Rao | C459: Male | D459: 36842 | E459: 9367862922 | F459: prasath458@gmail.com | G459: Salem | H459: Tamil Nadu | I459: South | J459: Bronze | K459: 43866
... A701: CUST0700 | B701: Radha Naicker | C701: Female | D701: 21870 | E701: 9158725903 | F701: radha700@gmail.com | G701: Kochi | H701: Kerala | I701: South | J701: Silver | K701: 43447

Sheet Sales Sheet
A1: Invoice_Number | B1: Transaction_Date | C1: Customer_ID | D1: Customer Name | E1: Membership | F1: Product_ID | G1: Product Name | H1: Catogory | I1: Store_ID | J1: Store Name | K1: Region | L1: Target | M1: Acheivements | N1: Employee_ID | O1: Employee Name | P1: Department | Q1: Quantity | R1: Unit_Price | S1: Discount_Pct | T1: Discount_Amount | U1: Sales_Amount | V1: Cost_Amount | W1: Profit | X1: Margin % | Y1: Payment_Mode | Z1: Return_Status | AA1: Sales_Channel | AB1: Order_Time | AC1: Time Category | AD1: Day_Type
A2: INV102500 | B2: 45872 | C2: CUST0486 | D2: Devi Pillai | E2: Bronze | F2: PRD024 | G2: Aavin Milk Pack v2 | H2: Dairy | I2: STR130 | J2: FreshMart Surat Central | K2: West | L2: 969110 | M2: 0.00066957311 | N2: EMP0066 | O2: Padma Raj | P2: Operations | Q2: 2 | R2: 313.47 | S2: 10 | T2: 62.69 | U2: 648.89 | V2: 492.24 | W2: 156.65 | X2: =(U2-V2)/U2 -> 0.24141226 | Y2: Cash | Z2: Not Returned | AA2: In-Store | AB2: 0.72777778 | AC2: =IF(HOUR(AB2)>=6,IF(HOUR(AB2)<12,"Morning",IF(HOUR(AB2)<17,"Afternoon",IF(HOUR(AB2)<21,"Evening","Night"))),"Night") -> Evening | AD2: Weekend
A3: INV102499 | B3: 46002 | C3: CUST0056 | D3: Nithya Prabhu | E3: Silver | F3: PRD012 | G3: Harvest Gold Rusk 1kg | H3: Bakery | I3: STR133 | J3: FreshMart Nagpur Gardens | K3: West | L3: 4934958 | M3: 0.00043878793 | N3: EMP0076 | O3: Meena Devi | P3: Inventory | Q3: 4 | R3: 541.35 | S3: 0 | T3: 0 | U3: 2165.4 | V3: 1345.6 | W3: 819.8 | X3: =(U3-V3)/U3 -> 0.37859056 | Y3: UPI | Z3: Not Returned | AA3: Online | AB3: 0.58472222 | AC3: =IF(HOUR(AB3)>=6,IF(HOUR(AB3)<12,"Morning",IF(HOUR(AB3)<17,"Afternoon",IF(HOUR(AB3)<21,"Evening","Night"))),"Night") -> Afternoon | AD3: Weekday
A4: INV102498 | B4: 46075 | C4: CUST0415 | D4: Bharath Devi | E4: Gold | F4: PRD033 | G4: Bisleri Soft Drinks 2kg | H4: Beverages | I4: STR054 | J4: FreshMart Mysuru Plaza | K4: South | L4: 538449 | M4: 0.0013585502 | N4: EMP0104 | O4: Pandi Nair | P4: Inventory | Q4: 3 | R4: 249.45 | S4: 15 | T4: 112.25 | U4: 731.51 | V4: 531.09 | W4: 200.42 | X4: =(U4-V4)/U4 -> 0.27398122 | Y4: Net Banking | Z4: Not Returned | AA4: In-Store | AB4: 0.84722222 | AC4: =IF(HOUR(AB4)>=6,IF(HOUR(AB4)<12,"Morning",IF(HOUR(AB4)<17,"Afternoon",IF(HOUR(AB4)<21,"Evening","Night"))),"Night") -> Evening | AD4: Weekend
A5: INV102497 | B5: 46033 | C5: CUST0080 | D5: Suresh Naidu | E5: Silver | F5: PRD109 | G5: Aachi Ponni Rice 1kg | H5: Rice | I5: STR083 | J5: FreshMart Salem Colony | K5: South | L5: 461555 | M5: 0.00070849628 | N5: EMP0074 | O5: Indira Varma | P5: Sales | Q5: 2 | R5: 157.98 | S5: 10 | T5: 31.6 | U5: 327.01 | V5: 275.9 | W5: 51.11 | X5: =(U5-V5)/U5 -> 0.15629491 | Y5: Net Banking | Z5: Not Returned | AA5: Mobile App | AB5: 0.89444444 | AC5: =IF(HOUR(AB5)>=6,IF(HOUR(AB5)<12,"Morning",IF(HOUR(AB5)<17,"Afternoon",IF(HOUR(AB5)<21,"Evening","Night"))),"Night") -> Night | AD5: Weekend
A6: INV102496 | B6: 45851 | C6: CUST0676 | D6: Dhanush Mudaliar | E6: Gold | F6: PRD050 | G6: Parle Namkeen 500g | H6: Snacks | I6: STR094 | J6: FreshMart Mumbai Central | K6: West | L6: 933757 | M6: 0.00029080371 | N6: EMP0008 | O6: Karthik Balan | P6: Store Manager | Q6: 5 | R6: 52.47 | S6: 10 | T6: 26.23 | U6: 271.54 | V6: 187.4 | W6: 84.14 | X6: =(U6-V6)/U6 -> 0.30986227 | Y6: Credit Card | Z6: Not Returned | AA6: In-Store | AB6: 0.38958333 | AC6: =IF(HOUR(AB6)>=6,IF(HOUR(AB6)<12,"Morning",IF(HOUR(AB6)<17,"Afternoon",IF(HOUR(AB6)<21,"Evening","Night"))),"Night") -> Morning | AD6: Weekend
A7: INV102495 | B7: 45997 | C7: CUST0293 | D7: Suresh Chandran | E7: Gold | F7: PRD059 | G7: Colgate Toothpaste 1kg | H7: Personal Care | I7: STR060 | J7: FreshMart Erode Square | K7: North | L7: 2220333 | M7: 0.0017738826 | N7: EMP0314 | O7: Naveen Naidu | P7: Cashier | Q7: 7 | R7: 575.61 | S7: 15 | T7: 604.39 | U7: 3938.61 | V7: 2543.03 | W7: 1395.58 | X7: =(U7-V7)/U7 -> 0.35433313 | Y7: Wallet | Z7: Returned | AA7: In-Store | AB7: 0.69375 | AC7: =IF(HOUR(AB7)>=6,IF(HOUR(AB7)<12,"Morning",IF(HOUR(AB7)<17,"Afternoon",IF(HOUR(AB7)<21,"Evening","Night"))),"Night") -> Afternoon | AD7: Weekend
A8: INV102494 | B8: 46098 | C8: CUST0101 | D8: Dinesh Nair | E8: Silver | F8: PRD034 | G8: Nescafe Coffee 500g | H8: Beverages | I8: STR061 | J8: FreshMart Hyderabad Colony | K8: South | L8: 2456631 | M8: 0.00015245269 | N8: EMP0279 | O8: Arun Varma | P8: Sales | Q8: 3 | R8: 124.84 | S8: 0 | T8: 0 | U8: 374.52 | V8: 292.05 | W8: 82.47 | X8: =(U8-V8)/U8 -> 0.22020186 | Y8: Cash | Z8: Not Returned | AA8: In-Store | AB8: 0.6125 | AC8: =IF(HOUR(AB8)>=6,IF(HOUR(AB8)<12,"Morning",IF(HOUR(AB8)<17,"Afternoon",IF(HOUR(AB8)<21,"Evening","Night"))),"Night") -> Afternoon | AD8: Weekday
A9: INV102493 | B9: 46096 | C9: CUST0616 | D9: Chitra Balan | E9: Bronze | F9: PRD002 | G9: Britannia Buns Pack | H9: Bakery | I9: STR092 | J9: FreshMart Chennai Gardens | K9: South | L9: 1922335 | M9: 0.0004743346 | N9: EMP0122 | O9: Rajesh Chettiar | P9: Cashier | Q9: 2 | R9: 440.5 | S9: 10 | T9: 88.1 | U9: 911.83 | V9: 508.1 | W9: 403.73 | X9: =(U9-V9)/U9 -> 0.44276894 | Y9: Wallet | Z9: Not Returned | AA9: Online | AB9: 0.6625 | AC9: =IF(HOUR(AB9)>=6,IF(HOUR(AB9)<12,"Morning",IF(HOUR(AB9)<17,"Afternoon",IF(HOUR(AB9)<21,"Evening","Night"))),"Night") -> Afternoon | AD9: Weekend
A10: INV102492 | B10: 45982 | C10: CUST0363 | D10: Elango Devi | E10: Bronze | F10: PRD048 | G10: Lays Chocolates 1kg | H10: Snacks | I10: STR071 | J10: FreshMart Salem Crossing | K10: South | L10: 518088 | M10: 0.00045619663 | N10: EMP0210 | O10: Karthik Venkataraman | P10: Sales | Q10: 2 | R10: 147.72 | S10: 20 | T10: 59.09 | U10: 236.35 | V10: 218.42 | W10: 17.93 | X10: =(U10-V10)/U10 -> 0.075862069 | Y10: Wallet | Z10: Not Returned | AA10: Mobile App | AB10: 0.70416667 | AC10: =IF(HOUR(AB10)>=6,IF(HOUR(AB10)<12,"Morning",IF(HOUR(AB10)<17,"Afternoon",IF(HOUR(AB10)<21,"Evening","Night"))),"Night") -> Afternoon | AD10: Weekday
A11: INV102491 | B11: 45886 | C11: CUST0616 | D11: Chitra Balan | E11: Bronze | F11: PRD006 | G11: Harvest Gold Cookies 500g | H11: Bakery | I11: STR124 | J11: FreshMart Ahmedabad Hub | K11: West | L11: 817396 | M11: 0.00082170698 | N11: EMP0294 | O11: Meena Prabhu | P11: Store Manager | Q11: 2 | R11: 343.56 | S11: 15 | T11: 103.07 | U11: 671.66 | V11: 432.64 | W11: 239.02 | X11: =(U11-V11)/U11 -> 0.35586457 | Y11: Wallet | Z11: Not Returned | AA11: In-Store | AB11: 0.39791667 | AC11: =IF(HOUR(AB11)>=6,IF(HOUR(AB11)<12,"Morning",IF(HOUR(AB11)<17,"Afternoon",IF(HOUR(AB11)<21,"Evening","Night"))),"Night") -> Morning | AD11: Weekend
A12: INV102490 | B12: 45912 | C12: CUST0243 | D12: Lakshmi Reddy | E12: Silver | F12: PRD083 | G12: Organic Fresh Fresh Fruits 2kg | H12: Fruits | I12: STR090 | J12: FreshMart Mysuru Heights | K12: South | L12: 2434234 | M12: 0.00029742416 | N12: EMP0209 | O12: Eswari Pandian | P12: Store Manager | Q12: 2 | R12: 425.88 | S12: 15 | T12: 127.76 | U12: 724 | V12: 714.94 | W12: 9.06 | X12: =(U12-V12)/U12 -> 0.012513812 | Y12: Debit Card | Z12: Not Returned | AA12: In-Store | AB12: 0.77916667 | AC12: =IF(HOUR(AB12)>=6,IF(HOUR(AB12)<12,"Morning",IF(HOUR(AB12)<17,"Afternoon",IF(HOUR(AB12)<21,"Evening","Night"))),"Night") -> Evening | AD12: Weekday
A13: INV102489 | B13: 45934 | C13: CUST0595 | D13: Lalitha Devi | E13: Bronze | F13: PRD044 | G13: ITC Frozen Vegetables 250ml v2 | H13: Frozen Foods | I13: STR051 | J13: FreshMart Madurai Arcade | K13: South | L13: 457604 | M13: 0.0011550598 | N13: EMP0156 | O13: Malathi Naicker | P13: Inventory | Q13: 2 | R13: 229.81 | S13: 0 | T13: 0 | U13: 528.56 | V13: 416.44 | W13: 112.12 | X13: =(U13-V13)/U13 -> 0.21212351 | Y13: Net Banking | Z13: Not Returned | AA13: Mobile App | AB13: 0.40902778 | AC13: =IF(HOUR(AB13)>=6,IF(HOUR(AB13)<12,"Morning",IF(HOUR(AB13)<17,"Afternoon",IF(HOUR(AB13)<21,"Evening","Night"))),"Night") -> Morning | AD13: Weekend
... A158: INV102345 | B158: 45943 | C158: CUST0324 | D158: Tamil Velan | E158: Gold | F158: PRD078 | G158: Vim Kitchenware Combo | H158: Household | I158: STR081 | J158: FreshMart Erode Crossing | K158: South | L158: 794126 | M158: 0.0027191655 | N158: EMP0226 | O158: Arun Rao | P158: Store Manager | Q158: 8 | R158: 269.92 | S158: 0 | T158: 0 | U158: 2159.36 | V158: 1720.24 | W158: 439.12 | X158: =(U158-V158)/U158 -> 0.20335655 | Y158: Cash | Z158: Not Returned | AA158: In-Store | AB158: 0.72083333 | AC158: =IF(HOUR(AB158)>=6,IF(HOUR(AB158)<12,"Morning",IF(HOUR(AB158)<17,"Afternoon",IF(HOUR(AB158)<21,"Evening","Night"))),"Night") -> Evening | AD158: Weekday
A159: INV102344 | B159: 45993 | C159: CUST0209 | D159: Udhay Pandian | E159: Gold | F159: PRD090 | G159: Organic Fresh Fresh Fruits Pack v2 | H159: Fruits | I159: STR021 | J159: FreshMart Madurai Market | K159: South | L159: 2110688 | M159: 0 | N159: EMP0280 | O159: Hema Mudaliar | P159: Store Manager | Q159: 7 | R159: 492.92 | S159: 10 | T159: 345.04 | U159: =Q159*R159-T159 -> 3105.4 | V159: 2591.26 | W159: 514.14 | X159: =(U159-V159)/U159 -> 0.16556321 | Y159: Credit Card | Z159: Not Returned | AA159: In-Store | AB159: 0.60694444 | AC159: =IF(HOUR(AB159)>=6,IF(HOUR(AB159)<12,"Morning",IF(HOUR(AB159)<17,"Afternoon",IF(HOUR(AB159)<21,"Evening","Night"))),"Night") -> Afternoon | AD159: Weekday
A160: INV102343 | B160: 45863 | C160: CUST0279 | D160: Ramesh Devi | E160: Gold | F160: PRD146 | G160: Lizol Floor Cleaner 200g | H160: Cleaning | I160: STR006 | J160: FreshMart Mysuru Junction | K160: South | L160: 2561982 | M160: 0.00012420072 | N160: EMP0265 | O160: Padma Subramaniam | P160: Operations | Q160: 5 | R160: 66.99 | S160: 5 | T160: 16.75 | U160: 318.2 | V160: 249.95 | W160: 68.25 | X160: =(U160-V160)/U160 -> 0.21448774 | Y160: Credit Card | Z160: Not Returned | AA160: In-Store | AB160: 0.72222222 | AC160: =IF(HOUR(AB160)>=6,IF(HOUR(AB160)<12,"Morning",IF(HOUR(AB160)<17,"Afternoon",IF(HOUR(AB160)<21,"Evening","Night"))),"Night") -> Evening | AD160: Weekday
A161: INV102342 | B161: 46072 | C161: CUST0361 | D161: Ramesh Achari | E161: Gold | F161: PRD082 | G161: Organic Fresh Fresh Fruits Pack | H161: Fruits | I161: STR118 | J161: FreshMart Surat Heights | K161: West | L161: 2120932 | M161: 0.000878411 | N161: EMP0223 | O161: Kalpana Varma | P161: HR | Q161: 7 | R161: 266.15 | S161: 0 | T161: 0 | U161: 1863.05 | V161: 1346.87 | W161: 516.18 | X161: =(U161-V161)/U161 -> 0.27706181 | Y161: UPI | Z161: Not Returned | AA161: Online | AB161: 0.73402778 | AC161: =IF(HOUR(AB161)>=6,IF(HOUR(AB161)<12,"Morning",IF(HOUR(AB161)<17,"Afternoon",IF(HOUR(AB161)<21,"Evening","Night"))),"Night") -> Evening | AD161: Weekday
A162: INV102341 | B162: 45912 | C162: CUST0675 | D162: Anand Chettiar | E162: Gold | F162: PRD111 | G162: Aachi Idli Rice 500g | H162: Rice | I162: STR076 | J162: FreshMart Hyderabad Towers | K162: South | L162: 1041021 | M162: 0.00066949658 | N162: EMP0056 | O162: Anjali Balan | P162: Sales | Q162: 3 | R162: 232.32 | S162: 0 | T162: 0 | U162: 696.96 | V162: 572.7 | W162: 124.26 | X162: =(U162-V162)/U162 -> 0.17828857 | Y162: Net Banking | Z162: Not Returned | AA162: In-Store | AB162: 0.6125 | AC162: =IF(HOUR(AB162)>=6,IF(HOUR(AB162)<12,"Morning",IF(HOUR(AB162)<17,"Afternoon",IF(HOUR(AB162)<21,"Evening","Night"))),"Night") -> Afternoon | AD162: Weekday
A163: INV102340 | B163: 45933 | C163: CUST0537 | D163: Ashok Balan | E163: Silver | F163: PRD035 | G163: Coca-Cola Coffee 500g | H163: Beverages | I163: STR011 | J163: FreshMart Bengaluru Enclave | K163: South | L163: 569084 | M163: 0.0044225457 | N163: EMP0102 | O163: Prasath Reddy | P163: Cashier | Q163: 5 | R163: 503.36 | S163: 0 | T163: 0 | U163: 2516.8 | V163: 1949 | W163: 567.8 | X163: =(U163-V163)/U163 -> 0.22560394 | Y163: Debit Card | Z163: Not Returned | AA163: In-Store | AB163: 0.50347222 | AC163: =IF(HOUR(AB163)>=6,IF(HOUR(AB163)<12,"Morning",IF(HOUR(AB163)<17,"Afternoon",IF(HOUR(AB163)<21,"Evening","Night"))),"Night") -> Afternoon | AD163: Weekday
A164: INV102339 | B164: 45775 | C164: CUST0179 | D164: Chitra Mudaliar | E164: Gold | F164: PRD119 | G164: Gold Winner Sunflower Oil 200g | H164: Oil | I164: STR070 | J164: FreshMart Bengaluru Nagar | K164: South | L164: 517547 | M164: 0.0027984705 | N164: EMP0072 | O164: Madhavan Venkataraman | P164: Sales | Q164: 6 | R164: 241.39 | S164: 0 | T164: 0 | U164: 1448.34 | V164: 1279.38 | W164: 168.96 | X164: =(U164-V164)/U164 -> 0.11665769 | Y164: Wallet | Z164: Not Returned | AA164: Online | AB164: 0.45694444 | AC164: =IF(HOUR(AB164)>=6,IF(HOUR(AB164)<12,"Morning",IF(HOUR(AB164)<17,"Afternoon",IF(HOUR(AB164)<21,"Evening","Night"))),"Night") -> Morning | AD164: Weekday
A165: INV102338 | B165: 45875 | C165: CUST0144 | D165: Lalitha Chandran | E165: Gold | F165: PRD029 | G165: Pepsi Tea 200g | H165: Beverages | I165: STR121 | J165: FreshMart Pune Junction | K165: West | L165: 542771 | M165: 0.0024853207 | N165: EMP0319 | O165: Harini Kumar | P165: Cashier | Q165: 5 | R165: 337.24 | S165: 20 | T165: 337.24 | U165: 1348.96 | V165: 1306.1 | W165: 42.86 | X165: =(U165-V165)/U165 -> 0.031772625 | Y165: Wallet | Z165: Not Returned | AA165: Mobile App | AB165: 0.84305556 | AC165: =IF(HOUR(AB165)>=6,IF(HOUR(AB165)<12,"Morning",IF(HOUR(AB165)<17,"Afternoon",IF(HOUR(AB165)<21,"Evening","Night"))),"Night") -> Evening | AD165: Weekday
A166: INV102337 | B166: 45982 | C166: CUST0186 | D166: Bhavani Pillai | E166: Bronze | F166: PRD024 | G166: Aavin Milk Pack v2 | H166: Dairy | I166: STR033 | J166: FreshMart Ahmedabad Complex | K166: South | L166: 1058381 | M166: 0.0010662417 | N166: EMP0024 | O166: Bhavani Kumar | P166: Cashier | Q166: 4 | R166: 313.47 | S166: 10 | T166: 125.39 | U166: 1128.49 | V166: 984.48 | W166: 144.01 | X166: =(U166-V166)/U166 -> 0.127613 | Y166: UPI | Z166: Not Returned | AA166: In-Store | AB166: 0.64791667 | AC166: =IF(HOUR(AB166)>=6,IF(HOUR(AB166)<12,"Morning",IF(HOUR(AB166)<17,"Afternoon",IF(HOUR(AB166)<21,"Evening","Night"))),"Night") -> Afternoon | AD166: Weekday
A167: INV102336 | B167: 46010 | C167: CUST0001 | D167: Revathi Balan | E167: Bronze | F167: PRD067 | G167: Dove Shampoo 500g | H167: Personal Care | I167: STR052 | J167: FreshMart Erode Extension | K167: South | L167: 5287316 | M167: 0.00010046307 | N167: EMP0205 | O167: Divya Menon | P167: Store Manager | Q167: 3 | R167: 186.38 | S167: 5 | T167: 27.96 | U167: 531.18 | V167: 406.98 | W167: 124.2 | X167: =(U167-V167)/U167 -> 0.23381904 | Y167: UPI | Z167: Not Returned | AA167: In-Store | AB167: 0.52777778 | AC167: =IF(HOUR(AB167)>=6,IF(HOUR(AB167)<12,"Morning",IF(HOUR(AB167)<17,"Afternoon",IF(HOUR(AB167)<21,"Evening","Night"))),"Night") -> Afternoon | AD167: Weekday
A168: INV102335 | B168: 45928 | C168: CUST0257 | D168: Eswari Sharma | E168: Silver | F168: PRD103 | G168: Organic Fresh Fresh Vegetables Pack | H168: Vegetables | I168: STR126 | J168: FreshMart Surat Hub | K168: West | L168: 2213249 | M168: 0.00035110374 | N168: EMP0063 | O168: Lakshmi Devi | P168: Store Manager | Q168: 2 | R168: 355.64 | S168: 5 | T168: 35.56 | U168: 777.08 | V168: 606.82 | W168: 170.26 | X168: =(U168-V168)/U168 -> 0.21910228 | Y168: Cash | Z168: Not Returned | AA168: In-Store | AB168: 0.8625 | AC168: =IF(HOUR(AB168)>=6,IF(HOUR(AB168)<12,"Morning",IF(HOUR(AB168)<17,"Afternoon",IF(HOUR(AB168)<21,"Evening","Night"))),"Night") -> Evening | AD168: Weekend
A169: INV102334 | B169: 45996 | C169: CUST0141 | D169: Jagan Rao | E169: Bronze | F169: PRD006 | G169: Harvest Gold Cookies 500g | H169: Bakery | I169: STR086 | J169: FreshMart Bengaluru Circle | K169: South | L169: 926537 | M169: 0.00088991589 | N169: EMP0263 | O169: Vani Nair | P169: Cashier | Q169: 3 | R169: 343.56 | S169: 20 | T169: 206.14 | U169: 824.54 | V169: 648.96 | W169: 175.58 | X169: =(U169-V169)/U169 -> 0.21294297 | Y169: Debit Card | Z169: Not Returned | AA169: Online | AB169: 0.79722222 | AC169: =IF(HOUR(AB169)>=6,IF(HOUR(AB169)<12,"Morning",IF(HOUR(AB169)<17,"Afternoon",IF(HOUR(AB169)<21,"Evening","Night"))),"Night") -> Evening | AD169: Weekday
A170: INV102333 | B170: 45954 | C170: CUST0253 | D170: Ovi Reddy | E170: Silver | F170: PRD129 | G170: Everest Powdered Spices Combo | H170: Masala | I170: STR092 | J170: FreshMart Chennai Gardens | K170: South | L170: 1922335 | M170: 0.00072678799 | N170: EMP0336 | O170: Sanjay Sharma | P170: Billing | Q170: 3 | R170: 490.22 | S170: 5 | T170: 73.53 | U170: 1397.13 | V170: 1120.74 | W170: 276.39 | X170: =(U170-V170)/U170 -> 0.19782697 | Y170: Credit Card | Z170: Not Returned | AA170: Online | AB170: 0.89861111 | AC170: =IF(HOUR(AB170)>=6,IF(HOUR(AB170)<12,"Morning",IF(HOUR(AB170)<17,"Afternoon",IF(HOUR(AB170)<21,"Evening","Night"))),"Night") -> Night | AD170: Weekday
A171: INV102331 | B171: 46038 | C171: CUST0178 | D171: Vasanth Varma | E171: Gold | F171: PRD026 | G171: Nescafe Coffee 1kg | H171: Beverages | I171: STR157 | J171: FreshMart Lucknow Extension | K171: North | L171: 562953 | M171: 0.0042023402 | N171: EMP0220 | O171: Ramesh Pillai | P171: Operations | Q171: 8 | R171: 347.9 | S171: 15 | T171: 417.48 | U171: 2365.72 | V171: 1978 | W171: 387.72 | X171: =(U171-V171)/U171 -> 0.16389091 | Y171: UPI | Z171: Not Returned | AA171: Online | AB171: 0.70833333 | AC171: =IF(HOUR(AB171)>=6,IF(HOUR(AB171)<12,"Morning",IF(HOUR(AB171)<17,"Afternoon",IF(HOUR(AB171)<21,"Evening","Night"))),"Night") -> Evening | AD171: Weekday
... A276: INV102225 | B276: 45942 | C276: CUST0096 | D276: Hariharan Gounder | E276: Gold | F276: PRD010 | G276: Harvest Gold Cookies Pack | H276: Bakery | I276: STR034 | J276: FreshMart Tiruppur Circle | K276: South | L276: 924804 | M276: 0.0012693068 | N276: EMP0034 | O276: Sangeetha Venkataraman | P276: Cashier | Q276: 5 | R276: 204.15 | S276: 0 | T276: 0 | U276: 1173.86 | V276: 538 | W276: 635.86 | X276: =(U276-V276)/U276 -> 0.54168299 | Y276: Wallet | Z276: Not Returned | AA276: In-Store | AB276: 0.55069444 | AC276: =IF(HOUR(AB276)>=6,IF(HOUR(AB276)<12,"Morning",IF(HOUR(AB276)<17,"Afternoon",IF(HOUR(AB276)<21,"Evening","Night"))),"Night") -> Afternoon | AD276: Weekend
A277: INV102224 | B277: 45997 | C277: CUST0573 | D277: Padma Varma | E277: Bronze | F277: PRD034 | G277: Nescafe Coffee 500g | H277: Beverages | I277: STR018 | J277: FreshMart Hyderabad Main Road | K277: South | L277: 970105 | M277: 0 | N277: EMP0308 | O277: Thenmozhi Selvam | P277: Cashier | Q277: 6 | R277: 128.81 | S277: 0 | T277: 0 | U277: =Q277*R277-T277 -> 772.86 | V277: 584.1 | W277: 304.69 | X277: =(U277-V277)/U277 -> 0.2442357 | Y277: Net Banking | Z277: Not Returned | AA277: In-Store | AB277: 0.50833333 | AC277: =IF(HOUR(AB277)>=6,IF(HOUR(AB277)<12,"Morning",IF(HOUR(AB277)<17,"Afternoon",IF(HOUR(AB277)<21,"Evening","Night"))),"Night") -> Afternoon | AD277: Weekend
A278: INV102223 | B278: 46012 | C278: CUST0110 | D278: Pandi Chandran | E278: Gold | F278: PRD100 | G278: Organic Fresh Fresh Vegetables 200g v2 | H278: Vegetables | I278: STR045 | J278: FreshMart Madurai Junction | K278: South | L278: 539795 | M278: 0.0024961143 | N278: EMP0204 | O278: Ramesh Murugan | P278: Inventory | Q278: 4 | R278: 292.91 | S278: 0 | T278: 0 | U278: 1347.39 | V278: 951.56 | W278: 395.83 | X278: =(U278-V278)/U278 -> 0.29377537 | Y278: UPI | Z278: Not Returned | AA278: In-Store | AB278: 0.87708333 | AC278: =IF(HOUR(AB278)>=6,IF(HOUR(AB278)<12,"Morning",IF(HOUR(AB278)<17,"Afternoon",IF(HOUR(AB278)<21,"Evening","Night"))),"Night") -> Night | AD278: Weekend
A279: INV102222 | B279: 46044 | C279: CUST0543 | D279: Gopal Menon | E279: Gold | F279: PRD125 | G279: Gold Winner Coconut Oil 2kg v2 | H279: Oil | I279: STR108 | J279: FreshMart Mumbai Square | K279: West | L279: 480418 | M279: 0.0020428877 | N279: EMP0171 | O279: Ashok Nair | P279: Cashier | Q279: 4 | R279: 245.36 | S279: 0 | T279: 0 | U279: 981.44 | V279: 781.76 | W279: 199.68 | X279: =(U279-V279)/U279 -> 0.20345615 | Y279: UPI | Z279: Not Returned | AA279: Mobile App | AB279: 0.53680556 | AC279: =IF(HOUR(AB279)>=6,IF(HOUR(AB279)<12,"Morning",IF(HOUR(AB279)<17,"Afternoon",IF(HOUR(AB279)<21,"Evening","Night"))),"Night") -> Afternoon | AD279: Weekday
A280: INV102221 | B280: 45949 | C280: CUST0254 | D280: Devi Raj | E280: Silver | F280: PRD052 | G280: Lays Namkeen 200g | H280: Snacks | I280: STR079 | J280: FreshMart Erode Hub | K280: South | L280: 2101567 | M280: 0.00089903867 | N280: EMP0295 | O280: Lakshmi Nair | P280: Inventory | Q280: 5 | R280: 328.59 | S280: 0 | T280: 0 | U280: 1889.39 | V280: 1277.45 | W280: 611.94 | X280: =(U280-V280)/U280 -> 0.32388231 | Y280: Debit Card | Z280: Not Returned | AA280: In-Store | AB280: 0.80694444 | AC280: =IF(HOUR(AB280)>=6,IF(HOUR(AB280)<12,"Morning",IF(HOUR(AB280)<17,"Afternoon",IF(HOUR(AB280)<21,"Evening","Night"))),"Night") -> Evening | AD280: Weekend
A281: INV102220 | B281: 45776 | C281: CUST0219 | D281: Pandi Naidu | E281: Gold | F281: PRD017 | G281: Nestle Curd 1kg | H281: Dairy | I281: STR044 | J281: FreshMart Erode Colony | K281: South | L281: 568216 | M281: 0.0033738226 | N281: EMP0287 | O281: Elango Gupta | P281: Store Manager | Q281: 4 | R281: 504.49 | S281: 5 | T281: 100.9 | U281: 1917.06 | V281: 1590.76 | W281: 326.3 | X281: =(U281-V281)/U281 -> 0.17020855 | Y281: Wallet | Z281: Not Returned | AA281: Online | AB281: 0.89791667 | AC281: =IF(HOUR(AB281)>=6,IF(HOUR(AB281)<12,"Morning",IF(HOUR(AB281)<17,"Afternoon",IF(HOUR(AB281)<21,"Evening","Night"))),"Night") -> Night | AD281: Weekday
A282: INV102219 | B282: 46059 | C282: CUST0186 | D282: Bhavani Pillai | E282: Bronze | F282: PRD050 | G282: Parle Namkeen 500g | H282: Snacks | I282: STR033 | J282: FreshMart Ahmedabad Complex | K282: South | L282: 1058381 | M282: 9.6997206e-05 | N282: EMP0313 | O282: Lokesh Varma | P282: HR | Q282: 2 | R282: 51.33 | S282: 0 | T282: 0 | U282: 102.66 | V282: 74.96 | W282: 27.7 | X282: =(U282-V282)/U282 -> 0.26982272 | Y282: Wallet | Z282: Not Returned | AA282: Online | AB282: 0.81944444 | AC282: =IF(HOUR(AB282)>=6,IF(HOUR(AB282)<12,"Morning",IF(HOUR(AB282)<17,"Afternoon",IF(HOUR(AB282)<21,"Evening","Night"))),"Night") -> Evening | AD282: Weekday
A283: INV102218 | B283: 45982 | C283: CUST0134 | D283: Balaji Chettiar | E283: Bronze | F283: PRD032 | G283: Coca-Cola Coffee Combo | H283: Beverages | I283: STR134 | J283: FreshMart Pune Extension | K283: West | L283: 2151660 | M283: 0.00011804839 | N283: EMP0013 | O283: Gokul Achari | P283: Billing | Q283: 2 | R283: 141.11 | S283: 10 | T283: 28.22 | U283: 254 | V283: 231.82 | W283: -382.91 | X283: =(U283-V283)/U283 -> 0.087322835 | Y283: Debit Card | Z283: Not Returned | AA283: In-Store | AB283: 0.88541667 | AC283: =IF(HOUR(AB283)>=6,IF(HOUR(AB283)<12,"Morning",IF(HOUR(AB283)<17,"Afternoon",IF(HOUR(AB283)<21,"Evening","Night"))),"Night") -> Night | AD283: Weekday
A284: INV102217 | B284: 45918 | C284: CUST0066 | D284: Bhavani Sharma | E284: Silver | F284: PRD118 | G284: Local Farm Fresh Fruits 1kg | H284: Oil | I284: STR095 | J284: FreshMart Ahmedabad Gardens | K284: West | L284: 1952402 | M284: 0.00031868437 | N284: EMP0177 | O284: Raghav Iyer | P284: Store Manager | Q284: 5 | R284: 155.55 | S284: 20 | T284: 155.55 | U284: 622.2 | V284: 688.2 | W284: -66 | X284: =(U284-V284)/U284 -> -0.10607522 | Y284: Credit Card | Z284: Not Returned | AA284: In-Store | AB284: 0.62152778 | AC284: =IF(HOUR(AB284)>=6,IF(HOUR(AB284)<12,"Morning",IF(HOUR(AB284)<17,"Afternoon",IF(HOUR(AB284)<21,"Evening","Night"))),"Night") -> Afternoon | AD284: Weekday
A285: INV102216 | B285: 46015 | C285: CUST0634 | D285: Chandrasekar Pandian | E285: Gold | F285: PRD126 | G285: Fortune Gingelly Oil 1L | H285: Oil | I285: STR056 | J285: FreshMart Bengaluru Junction | K285: South | L285: 4116030 | M285: 0.00028050087 | N285: EMP0163 | O285: Revathi Raj | P285: Cashier | Q285: 3 | R285: 384.85 | S285: 0 | T285: 0 | U285: 1154.55 | V285: 973.44 | W285: 181.11 | X285: =(U285-V285)/U285 -> 0.15686631 | Y285: Debit Card | Z285: Not Returned | AA285: Online | AB285: 0.7 | AC285: =IF(HOUR(AB285)>=6,IF(HOUR(AB285)<12,"Morning",IF(HOUR(AB285)<17,"Afternoon",IF(HOUR(AB285)<21,"Evening","Night"))),"Night") -> Afternoon | AD285: Weekday
A286: INV102215 | B286: 45984 | C286: CUST0199 | D286: Sanjay Gupta | E286: Bronze | F286: PRD125 | G286: Gold Winner Coconut Oil 2kg v2 | H286: Oil | I286: STR068 | J286: FreshMart Coimbatore Main Road | K286: South | L286: 456496 | M286: 0.0021001936 | N286: EMP0304 | O286: Deepa Menon | P286: Billing | Q286: 4 | R286: 219.39 | S286: 5 | T286: 43.88 | U286: 958.73 | V286: 781.76 | W286: 176.97 | X286: =(U286-V286)/U286 -> 0.18458794 | Y286: Wallet | Z286: Not Returned | AA286: In-Store | AB286: 0.44236111 | AC286: =IF(HOUR(AB286)>=6,IF(HOUR(AB286)<12,"Morning",IF(HOUR(AB286)<17,"Afternoon",IF(HOUR(AB286)<21,"Evening","Night"))),"Night") -> Morning | AD286: Weekend
A287: INV102214 | B287: 45816 | C287: CUST0567 | D287: Bharath Balan | E287: Gold | F287: PRD101 | G287: Organic Fresh Fresh Vegetables 500g | H287: Vegetables | I287: STR061 | J287: FreshMart Hyderabad Colony | K287: South | L287: 2456631 | M287: 0.0015291389 | N287: EMP0329 | O287: Balamurugan Nair | P287: Cashier | Q287: 7 | R287: 518.5 | S287: 10 | T287: 362.95 | U287: 3756.53 | V287: 2710.12 | W287: 1046.41 | X287: =(U287-V287)/U287 -> 0.27855761 | Y287: Cash | Z287: Not Returned | AA287: Mobile App | AB287: 0.45 | AC287: =IF(HOUR(AB287)>=6,IF(HOUR(AB287)<12,"Morning",IF(HOUR(AB287)<17,"Afternoon",IF(HOUR(AB287)<21,"Evening","Night"))),"Night") -> Morning | AD287: Weekend
A288: INV102213 | B288: 45921 | C288: CUST0063 | D288: Priya Varma | E288: Gold | F288: PRD078 | G288: Vim Kitchenware Combo | H288: Household | I288: STR143 | J288: FreshMart Jaipur Colony | K288: North | L288: 2471169 | M288: 0.00078944014 | N288: EMP0338 | O288: Revathi Sekar | P288: Sales | Q288: 8 | R288: 265.06 | S288: 20 | T288: 424.1 | U288: 1950.84 | V288: 1720.24 | W288: 230.6 | X288: =(U288-V288)/U288 -> 0.11820549 | Y288: Debit Card | Z288: Not Returned | AA288: In-Store | AB288: 0.81805556 | AC288: =IF(HOUR(AB288)>=6,IF(HOUR(AB288)<12,"Morning",IF(HOUR(AB288)<17,"Afternoon",IF(HOUR(AB288)<21,"Evening","Night"))),"Night") -> Evening | AD288: Weekend
A289: INV102212 | B289: 46096 | C289: CUST0246 | D289: Udhay Varma | E289: Gold | F289: PRD086 | G289: Local Farm Fresh Fruits Combo v2 | H289: Fruits | I289: STR072 | J289: FreshMart Salem Point | K289: South | L289: 3875742 | M289: 0.00032033866 | N289: EMP0124 | O289: Vijay Pandian | P289: Sales | Q289: 0 | R289: 359.87 | S289: 0 | T289: 0 | U289: 1241.55 | V289: 823.83 | W289: 417.72 | X289: =(U289-V289)/U289 -> 0.3364504 | Y289: Net Banking | Z289: Not Returned | AA289: Online | AB289: 0.69166667 | AC289: =IF(HOUR(AB289)>=6,IF(HOUR(AB289)<12,"Morning",IF(HOUR(AB289)<17,"Afternoon",IF(HOUR(AB289)<21,"Evening","Night"))),"Night") -> Afternoon | AD289: Weekend
... A368: INV102132 | B368: 45936 | C368: CUST0205 | D368: Lalitha Nathan | E368: Gold | F368: PRD148 | G368: Lizol Toilet Cleaner 200g | H368: Cleaning | I368: STR097 | J368: FreshMart Ahmedabad Arcade | K368: West | L368: 2632479 | M368: 0.00019920767 | N368: EMP0340 | O368: Nithya Subramaniam | P368: Cashier | Q368: 5 | R368: 123.39 | S368: 15 | T368: 92.54 | U368: 524.41 | V368: 416.65 | W368: 107.76 | X368: =(U368-V368)/U368 -> 0.20548807 | Y368: Cash | Z368: Not Returned | AA368: Online | AB368: 0.77222222 | AC368: =IF(HOUR(AB368)>=6,IF(HOUR(AB368)<12,"Morning",IF(HOUR(AB368)<17,"Afternoon",IF(HOUR(AB368)<21,"Evening","Night"))),"Night") -> Evening | AD368: Weekday
A369: INV102131 | B369: 46107 | C369: CUST0540 | D369: Thenmozhi Naicker | E369: Gold | F369: PRD049 | G369: Cadbury Chips 1kg | H369: Snacks | I369: Missing Store Id | J369: Missing Store | K369: South | L369: =AVERAGE($L$2:$L$1172) -> 1985720.4 | N369: EMP0157 | O369: Elango Velan | P369: Cashier | Q369: 3 | R369: 465.22 | S369: 0 | T369: 0 | U369: 1395.66 | V369: 926.82 | W369: 468.84 | X369: =(U369-V369)/U369 -> 0.33592709 | Y369: Debit Card | Z369: Not Returned | AA369: In-Store | AB369: 0.43958333 | AC369: =IF(HOUR(AB369)>=6,IF(HOUR(AB369)<12,"Morning",IF(HOUR(AB369)<17,"Afternoon",IF(HOUR(AB369)<21,"Evening","Night"))),"Night") -> Morning | AD369: Weekday
A370: INV102130 | B370: 46056 | C370: CUST0412 | D370: Kalpana Gounder | E370: Gold | F370: PRD029 | G370: Pepsi Tea 200g | H370: Beverages | I370: STR107 | J370: FreshMart Surat Arcade | K370: West | L370: 1016387 | M370: 0.0027961987 | N370: EMP0146 | O370: Kishore Chettiar | P370: Inventory | Q370: 8 | R370: 373.95 | S370: 5 | T370: 149.58 | U370: 2842.02 | V370: 2089.76 | W370: 752.26 | X370: =(U370-V370)/U370 -> 0.26469201 | Y370: Credit Card | Z370: Not Returned | AA370: Online | AB370: 0.63263889 | AC370: =IF(HOUR(AB370)>=6,IF(HOUR(AB370)<12,"Morning",IF(HOUR(AB370)<17,"Afternoon",IF(HOUR(AB370)<21,"Evening","Night"))),"Night") -> Afternoon | AD370: Weekday
A371: INV102129 | B371: 45938 | C371: CUST0406 | D371: Gopal Naidu | E371: Gold | F371: PRD085 | G371: Local Farm Fresh Fruits 1kg | H371: Fruits | I371: STR063 | J371: FreshMart Hyderabad Market | K371: South | L371: 1996693 | M371: 0.00053804466 | N371: EMP0051 | O371: Thenmozhi Prabhu | P371: Billing | Q371: 3 | R371: 447.63 | S371: 20 | T371: 268.58 | U371: 1074.31 | V371: 1008.21 | W371: 66.1 | X371: =(U371-V371)/U371 -> 0.061527864 | Y371: Debit Card | Z371: Not Returned | AA371: In-Store | AB371: 0.81319444 | AC371: =IF(HOUR(AB371)>=6,IF(HOUR(AB371)<12,"Morning",IF(HOUR(AB371)<17,"Afternoon",IF(HOUR(AB371)<21,"Evening","Night"))),"Night") -> Evening | AD371: Weekday
A372: INV102128 | B372: 46080 | C372: CUST0182 | D372: Esha Prabhu | E372: Silver | F372: PRD005 | G372: Amul Paneer 250ml | H372: Bakery | I372: STR073 | J372: FreshMart Bengaluru Market | K372: South | L372: 4760462 | M372: 0.00022366947 | N372: EMP0268 | O372: Dhanya Sharma | P372: Store Manager | Q372: 4 | R372: 332.74 | S372: 20 | T372: 266.19 | U372: 1064.77 | V372: 821.08 | W372: 243.69 | X372: =(U372-V372)/U372 -> 0.22886633 | Y372: Cash | Z372: Not Returned | AA372: In-Store | AB372: 0.55833333 | AC372: =IF(HOUR(AB372)>=6,IF(HOUR(AB372)<12,"Morning",IF(HOUR(AB372)<17,"Afternoon",IF(HOUR(AB372)<21,"Evening","Night"))),"Night") -> Afternoon | AD372: Weekday
A373: INV102127 | B373: 45857 | C373: CUST0437 | D373: Vasanth Krishnan | E373: Silver | F373: PRD124 | G373: Gold Winner Coconut Oil 2kg | H373: Oil | I373: STR164 | J373: FreshMart Delhi Towers | K373: North | L373: 808195 | M373: 0.00086726594 | N373: EMP0309 | O373: Kannan Kumar | P373: Sales | Q373: 5 | R373: 121.9 | S373: 0 | T373: 0 | U373: 700.92 | V373: 544.6 | W373: 156.32 | X373: =(U373-V373)/U373 -> 0.22302117 | Y373: UPI | Z373: Not Returned | AA373: In-Store | AB373: 0.78888889 | AC373: =IF(HOUR(AB373)>=6,IF(HOUR(AB373)<12,"Morning",IF(HOUR(AB373)<17,"Afternoon",IF(HOUR(AB373)<21,"Evening","Night"))),"Night") -> Evening | AD373: Weekend
A374: INV102126 | B374: 45800 | C374: CUST0588 | D374: Arun Menon | E374: Bronze | F374: PRD100 | G374: Organic Fresh Fresh Vegetables 200g v2 | H374: Vegetables | I374: STR006 | J374: FreshMart Mysuru Junction | K374: South | L374: 2561982 | M374: 0.00011336926 | N374: EMP0265 | O374: Padma Subramaniam | P374: Operations | Q374: 1 | R374: 290.45 | S374: 0 | T374: 0 | U374: 290.45 | V374: 237.89 | W374: 52.56 | X374: =(U374-V374)/U374 -> 0.18096058 | Y374: Debit Card | Z374: Not Returned | AA374: Mobile App | AB374: 0.53611111 | AC374: =IF(HOUR(AB374)>=6,IF(HOUR(AB374)<12,"Morning",IF(HOUR(AB374)<17,"Afternoon",IF(HOUR(AB374)<21,"Evening","Night"))),"Night") -> Afternoon | AD374: Weekday
A375: INV102125 | B375: 46004 | C375: CUST0157 | D375: Prasath Chettiar | E375: Gold | F375: PRD129 | G375: Everest Powdered Spices Combo | H375: Masala | I375: STR153 | J375: FreshMart Lucknow Junction | K375: North | L375: 4459489 | M375: 0.0003416804 | N375: EMP0333 | O375: Vasanthi Velan | P375: Cashier | Q375: 3 | R375: 490.73 | S375: 10 | T375: 147.22 | U375: 1523.72 | V375: 1120.74 | W375: 402.98 | X375: =(U375-V375)/U375 -> 0.26447116 | Y375: Wallet | Z375: Not Returned | AA375: Online | AB375: 0.62361111 | AC375: =IF(HOUR(AB375)>=6,IF(HOUR(AB375)<12,"Morning",IF(HOUR(AB375)<17,"Afternoon",IF(HOUR(AB375)<21,"Evening","Night"))),"Night") -> Afternoon | AD375: Weekend
A376: INV102124 | B376: 45748 | C376: CUST0246 | D376: Udhay Varma | E376: Gold | F376: PRD089 | G376: Organic Fresh Fresh Fruits 500g | H376: Fruits | I376: STR126 | J376: FreshMart Surat Hub | K376: West | L376: 2213249 | M376: 0.00066416838 | N376: EMP0080 | O376: Charulatha Balan | P376: Sales | Q376: 5 | R376: 326.66 | S376: 10 | T376: 163.33 | U376: 1469.97 | V376: 1257.1 | W376: 212.87 | X376: =(U376-V376)/U376 -> 0.14481248 | Y376: Net Banking | Z376: Not Returned | AA376: In-Store | AB376: 0.59305556 | AC376: =IF(HOUR(AB376)>=6,IF(HOUR(AB376)<12,"Morning",IF(HOUR(AB376)<17,"Afternoon",IF(HOUR(AB376)<21,"Evening","Night"))),"Night") -> Afternoon | AD376: Weekday
A377: INV102123 | B377: 45885 | C377: CUST0370 | D377: Jaya Naicker | E377: Gold | F377: PRD020 | G377: Aavin Milk 1L | H377: Dairy | I377: STR049 | J377: FreshMart Mysuru Circle | K377: South | L377: 968457 | M377: 0.00043462952 | N377: EMP0113 | O377: Radha Rao | P377: Inventory | Q377: 4 | R377: 114.38 | S377: 20 | T377: 91.5 | U377: 420.92 | V377: 344.2 | W377: 76.72 | X377: =(U377-V377)/U377 -> 0.18226741 | Y377: UPI | Z377: Not Returned | AA377: In-Store | AB377: 0.67430556 | AC377: =IF(HOUR(AB377)>=6,IF(HOUR(AB377)<12,"Morning",IF(HOUR(AB377)<17,"Afternoon",IF(HOUR(AB377)<21,"Evening","Night"))),"Night") -> Afternoon | AD377: Weekend
A378: INV102122 | B378: 46065 | C378: CUST0424 | D378: Sanjay Varma | E378: Bronze | F378: PRD054 | G378: Lays Namkeen 2kg | H378: Snacks | I378: STR064 | J378: FreshMart Kochi Extension | K378: South | L378: 5240750 | M378: 0.00019220531 | N378: EMP0234 | O378: Lalitha Menon | P378: Sales | Q378: 2 | R378: 530.16 | S378: 5 | T378: 53.02 | U378: 1007.3 | V378: 758.38 | W378: 248.92 | X378: =(U378-V378)/U378 -> 0.24711605 | Y378: Wallet | Z378: Not Returned | AA378: In-Store | AB378: 0.41180556 | AC378: =IF(HOUR(AB378)>=6,IF(HOUR(AB378)<12,"Morning",IF(HOUR(AB378)<17,"Afternoon",IF(HOUR(AB378)<21,"Evening","Night"))),"Night") -> Morning | AD378: Weekday
A379: INV102121 | B379: 45938 | C379: CUST0179 | D379: Chitra Mudaliar | E379: Gold | F379: PRD055 | G379: Cadbury Biscuits Pack | H379: Snacks | I379: STR009 | J379: FreshMart Kochi Square | K379: South | L379: 429599 | M379: 0.0018912055 | N379: EMP0317 | O379: Umesh Sharma | P379: HR | Q379: 6 | R379: 135.41 | S379: 0 | T379: 0 | U379: 812.46 | V379: 574.2 | W379: 238.26 | X379: =(U379-V379)/U379 -> 0.29325751 | Y379: UPI | Z379: Returned | AA379: In-Store | AB379: 0.81736111 | AC379: =IF(HOUR(AB379)>=6,IF(HOUR(AB379)<12,"Morning",IF(HOUR(AB379)<17,"Afternoon",IF(HOUR(AB379)<21,"Evening","Night"))),"Night") -> Evening | AD379: Weekday
A380: INV102120 | B380: 45808 | C380: CUST0490 | D380: Hema Gounder | E380: Gold | F380: PRD136 | G380: Aachi Whole Spices 200g v2 | H380: Masala | I380: STR063 | J380: FreshMart Hyderabad Market | K380: South | L380: 1996693 | M380: 0.00029548859 | N380: EMP0233 | O380: Sangeetha Balan | P380: Sales | Q380: 4 | R380: 128.26 | S380: 0 | T380: 0 | U380: 590 | V380: 364.72 | W380: 225.28 | X380: =(U380-V380)/U380 -> 0.38183051 | Y380: Cash | Z380: Not Returned | AA380: In-Store | AB380: 0.82083333 | AC380: =IF(HOUR(AB380)>=6,IF(HOUR(AB380)<12,"Morning",IF(HOUR(AB380)<17,"Afternoon",IF(HOUR(AB380)<21,"Evening","Night"))),"Night") -> Evening | AD380: Weekend
A381: INV102119 | B381: 45825 | C381: CUST0396 | D381: Yogesh Raj | E381: Silver | F381: PRD142 | G381: Lizol Dishwash 200g | H381: Cleaning | I381: STR148 | J381: FreshMart Kanpur Gardens | K381: North | L381: 2474333 | M381: 0.00035917963 | N381: EMP0267 | O381: Ashok Pillai | P381: HR | Q381: 2 | R381: 522.78 | S381: 15 | T381: 156.83 | U381: 888.73 | V381: 791.74 | W381: 96.99 | X381: =(U381-V381)/U381 -> 0.10913326 | Y381: Net Banking | Z381: Not Returned | AA381: In-Store | AB381: 0.59236111 | AC381: =IF(HOUR(AB381)>=6,IF(HOUR(AB381)<12,"Morning",IF(HOUR(AB381)<17,"Afternoon",IF(HOUR(AB381)<21,"Evening","Night"))),"Night") -> Afternoon | AD381: Weekday
... A426: INV102074 | B426: 46013 | C426: CUST0507 | D426: Kamala Iyer | E426: Silver | F426: PRD108 | G426: Daawat Basmati Rice 2kg | H426: Rice | I426: STR021 | J426: FreshMart Madurai Market | K426: South | L426: 2110688 | M426: 0.00065371576 | N426: EMP0280 | O426: Hema Mudaliar | P426: Store Manager | Q426: 5 | R426: 306.62 | S426: 10 | T426: 153.31 | U426: 1379.79 | V426: 1299.65 | W426: 80.14 | X426: =(U426-V426)/U426 -> 0.058081302 | Y426: Net Banking | Z426: Not Returned | AA426: In-Store | AB426: 0.56805556 | AC426: =IF(HOUR(AB426)>=6,IF(HOUR(AB426)<12,"Morning",IF(HOUR(AB426)<17,"Afternoon",IF(HOUR(AB426)<21,"Evening","Night"))),"Night") -> Afternoon | AD426: Weekday
A427: INV102073 | B427: 45880 | C427: CUST0272 | D427: Prakash Kumar | E427: Bronze | F427: PRD037 | G427: ITC Frozen Snacks 250ml | H427: Frozen Foods | I427: Missing Store Id | J427: Missing Store | K427: South | L427: =AVERAGE($L$2:$L$1172) -> 1985720.4 | N427: EMP0280 | O427: Hema Mudaliar | P427: Store Manager | Q427: 1 | R427: 245.32 | S427: 15 | T427: 36.8 | U427: 208.52 | V427: 209.38 | W427: -0.86 | X427: =(U427-V427)/U427 -> -0.0041243046 | Y427: Debit Card | Z427: Not Returned | AA427: In-Store | AB427: 0.87569444 | AC427: =IF(HOUR(AB427)>=6,IF(HOUR(AB427)<12,"Morning",IF(HOUR(AB427)<17,"Afternoon",IF(HOUR(AB427)<21,"Evening","Night"))),"Night") -> Night | AD427: Weekday
A428: INV102072 | B428: 45949 | C428: CUST0572 | D428: Chandrasekar Balan | E428: Gold | F428: PRD104 | G428: Local Farm Fresh Vegetables Combo | H428: Vegetables | I428: STR048 | J428: FreshMart Bengaluru Square | K428: South | L428: 2183318 | M428: 0.00074850755 | N428: EMP0312 | O428: Vasanthi Chettiar | P428: Sales | Q428: 7 | R428: 203.01 | S428: 0 | T428: 0 | U428: 1634.23 | V428: 1073.94 | W428: 560.29 | X428: =(U428-V428)/U428 -> 0.34284648 | Y428: Cash | Z428: Not Returned | AA428: Mobile App | AB428: 0.72847222 | AC428: =IF(HOUR(AB428)>=6,IF(HOUR(AB428)<12,"Morning",IF(HOUR(AB428)<17,"Afternoon",IF(HOUR(AB428)<21,"Evening","Night"))),"Night") -> Evening | AD428: Weekend
A429: INV102071 | B429: 46084 | C429: CUST0291 | D429: Revathi Sharma | E429: Bronze | F429: PRD016 | G429: Milky Mist Milk 2kg | H429: Dairy | I429: STR069 | J429: FreshMart Madurai Gardens | K429: South | L429: 503493 | M429: 0.00035702582 | N429: EMP0283 | O429: Suresh Pandian | P429: Sales | Q429: 3 | R429: 59.92 | S429: 0 | T429: 0 | U429: 179.76 | V429: 144.45 | W429: 35.31 | X429: =(U429-V429)/U429 -> 0.19642857 | Y429: Credit Card | Z429: Not Returned | AA429: In-Store | AB429: 0.55486111 | AC429: =IF(HOUR(AB429)>=6,IF(HOUR(AB429)<12,"Morning",IF(HOUR(AB429)<17,"Afternoon",IF(HOUR(AB429)<21,"Evening","Night"))),"Night") -> Afternoon | AD429: Weekday
A430: INV102070 | B430: 45942 | C430: CUST0045 | D430: Thenmozhi Pandian | E430: Gold | F430: PRD048 | G430: Lays Chocolates 1kg | H430: Snacks | I430: STR046 | J430: FreshMart Mysuru Colony | K430: South | L430: 808240 | M430: 0.001534705 | N430: EMP0023 | O430: Jayakumar Gounder | P430: Operations | Q430: 8 | R430: 158.62 | S430: 15 | T430: 190.34 | U430: 1240.41 | V430: 873.68 | W430: 366.73 | X430: =(U430-V430)/U430 -> 0.29565224 | Y430: Cash | Z430: Not Returned | AA430: In-Store | AB430: 0.40555556 | AC430: =IF(HOUR(AB430)>=6,IF(HOUR(AB430)<12,"Morning",IF(HOUR(AB430)<17,"Afternoon",IF(HOUR(AB430)<21,"Evening","Night"))),"Night") -> Morning | AD430: Weekend
A431: INV102069 | B431: 46075 | C431: CUST0191 | D431: Elango Balan | E431: Bronze | F431: PRD137 | G431: MDH Powdered Spices 200g | H431: Masala | I431: STR013 | J431: FreshMart Tiruppur Extension | K431: South | L431: 2203116 | M431: 0.0002307913 | N431: EMP0017 | O431: Ovi Sharma | P431: Sales | Q431: 1 | R431: 442.14 | S431: 0 | T431: 0 | U431: 508.46 | V431: 351.87 | W431: 156.59 | X431: =(U431-V431)/U431 -> 0.30796916 | Y431: Cash | Z431: Not Returned | AA431: In-Store | AB431: 0.7 | AC431: =IF(HOUR(AB431)>=6,IF(HOUR(AB431)<12,"Morning",IF(HOUR(AB431)<17,"Afternoon",IF(HOUR(AB431)<21,"Evening","Night"))),"Night") -> Afternoon | AD431: Weekend
A432: INV102068 | B432: 46037 | C432: CUST0474 | D432: Geetha Venkataraman | E432: Bronze | F432: PRD131 | G432: Sakthi Powdered Spices 250ml | H432: Masala | I432: STR055 | J432: FreshMart Madurai Circle | K432: South | L432: 2005131 | M432: 7.9246693e-05 | N432: EMP0068 | O432: Manoj Subramaniam | P432: Sales | Q432: 2 | R432: 93.47 | S432: 15 | T432: 28.04 | U432: 158.9 | V432: 144.58 | W432: 14.32 | X432: =(U432-V432)/U432 -> 0.090119572 | Y432: Wallet | Z432: Not Returned | AA432: In-Store | AB432: 0.87916667 | AC432: =IF(HOUR(AB432)>=6,IF(HOUR(AB432)<12,"Morning",IF(HOUR(AB432)<17,"Afternoon",IF(HOUR(AB432)<21,"Evening","Night"))),"Night") -> Night | AD432: Weekday
A433: INV102067 | B433: 45942 | C433: CUST0505 | D433: Yazhini Sekar | E433: Gold | F433: PRD011 | G433: Britannia Rusk 1L | H433: Bakery | I433: STR029 | J433: FreshMart Bengaluru Colony | K433: South | L433: 4433499 | M433: 0.00024069928 | N433: EMP0182 | O433: Arun Naicker | P433: Operations | Q433: 5 | R433: 185.59 | S433: 0 | T433: 0 | U433: 1067.14 | V433: 511.15 | W433: 555.99 | X433: =(U433-V433)/U433 -> 0.52100943 | Y433: Wallet | Z433: Not Returned | AA433: In-Store | AB433: 0.59513889 | AC433: =IF(HOUR(AB433)>=6,IF(HOUR(AB433)<12,"Morning",IF(HOUR(AB433)<17,"Afternoon",IF(HOUR(AB433)<21,"Evening","Night"))),"Night") -> Afternoon | AD433: Weekend
A434: INV102066 | B434: 45917 | C434: CUST0599 | D434: Kalpana Subramaniam | E434: Gold | F434: PRD027 | G434: Coca-Cola Tea 1kg | H434: Beverages | I434: STR022 | J434: FreshMart Tiruppur Complex | K434: South | L434: 4327607 | M434: 0.00021896166 | N434: EMP0283 | O434: Suresh Pandian | P434: Sales | Q434: 6 | R434: 157.93 | S434: 0 | T434: 0 | U434: 947.58 | V434: 641.94 | W434: 305.64 | X434: =(U434-V434)/U434 -> 0.32254796 | Y434: Credit Card | Z434: Not Returned | AA434: Online | AB434: 0.79444444 | AC434: =IF(HOUR(AB434)>=6,IF(HOUR(AB434)<12,"Morning",IF(HOUR(AB434)<17,"Afternoon",IF(HOUR(AB434)<21,"Evening","Night"))),"Night") -> Evening | AD434: Weekday
A435: INV102065 | B435: 46018 | C435: CUST0499 | D435: Rajesh Rao | E435: Gold | F435: PRD135 | G435: MDH Whole Spices 1L | H435: Masala | I435: STR115 | J435: FreshMart Surat Nagar | K435: West | L435: 767131 | M435: 0.0024782338 | N435: EMP0327 | O435: Yogesh Varma | P435: Inventory | Q435: 5 | R435: 413.29 | S435: 20 | T435: 413.29 | U435: 1901.13 | V435: 1465.25 | W435: 435.88 | X435: =(U435-V435)/U435 -> 0.22927417 | Y435: Credit Card | Z435: Not Returned | AA435: In-Store | AB435: 0.81666667 | AC435: =IF(HOUR(AB435)>=6,IF(HOUR(AB435)<12,"Morning",IF(HOUR(AB435)<17,"Afternoon",IF(HOUR(AB435)<21,"Evening","Night"))),"Night") -> Evening | AD435: Weekend
A436: INV102064 | B436: 45820 | C436: CUST0468 | D436: Dinesh Kumar | E436: Silver | F436: PRD094 | G436: Organic Fresh Fresh Vegetables 2kg | H436: Vegetables | I436: STR020 | J436: FreshMart Erode Circle | K436: South | L436: 4909566 | M436: 0.00016425892 | N436: EMP0321 | O436: Sundar Velan | P436: Cashier | Q436: 3 | R436: 298.68 | S436: 10 | T436: 89.6 | U436: 806.44 | V436: 752.07 | W436: 54.37 | X436: =(U436-V436)/U436 -> 0.067419771 | Y436: Debit Card | Z436: Not Returned | AA436: Mobile App | AB436: 0.45069444 | AC436: =IF(HOUR(AB436)>=6,IF(HOUR(AB436)<12,"Morning",IF(HOUR(AB436)<17,"Afternoon",IF(HOUR(AB436)<21,"Evening","Night"))),"Night") -> Morning | AD436: Weekday
A437: INV102063 | B437: 45909 | C437: CUST0099 | D437: Lakshmi Krishnan | E437: Silver | F437: PRD031 | G437: Nescafe Coffee Pack | H437: Beverages | I437: STR117 | J437: FreshMart Nagpur Market | K437: South | L437: 820955 | M437: 0.0017728743 | N437: EMP0009 | O437: Usha Chettiar | P437: Cashier | Q437: 5 | R437: 342.46 | S437: 15 | T437: 256.85 | U437: 1455.45 | V437: 1358.9 | W437: 96.55 | X437: =(U437-V437)/U437 -> 0.066336872 | Y437: UPI | Z437: Not Returned | AA437: Online | AB437: 0.38541667 | AC437: =IF(HOUR(AB437)>=6,IF(HOUR(AB437)<12,"Morning",IF(HOUR(AB437)<17,"Afternoon",IF(HOUR(AB437)<21,"Evening","Night"))),"Night") -> Morning | AD437: Weekday
A438: INV102062 | B438: 45756 | C438: CUST0572 | D438: Chandrasekar Balan | E438: Gold | F438: PRD004 | G438: Britannia Buns 2kg | H438: Bakery | I438: STR165 | J438: FreshMart Jaipur Junction | K438: North | L438: 4786252 | M438: 0.00060454819 | N438: EMP0260 | O438: Kamala Prabhu | P438: Billing | Q438: 7 | R438: 413.36 | S438: 0 | T438: 0 | U438: 2893.52 | V438: 1655.78 | W438: 1237.74 | X438: =(U438-V438)/U438 -> 0.42776272 | Y438: Wallet | Z438: Not Returned | AA438: Mobile App | AB438: 0.91180556 | AC438: =IF(HOUR(AB438)>=6,IF(HOUR(AB438)<12,"Morning",IF(HOUR(AB438)<17,"Afternoon",IF(HOUR(AB438)<21,"Evening","Night"))),"Night") -> Night | AD438: Weekday
A439: INV102061 | B439: 45826 | C439: CUST0085 | D439: Sundar Prabhu | E439: Bronze | F439: PRD024 | G439: Aavin Milk Pack v2 | H439: Dairy | I439: STR082 | J439: FreshMart Salem Bypass | K439: South | L439: 5200952 | M439: 0.00010848975 | N439: EMP0115 | O439: Vasanth Menon | P439: Store Manager | Q439: 2 | R439: 313.47 | S439: 10 | T439: 62.69 | U439: 564.25 | V439: 492.24 | W439: 72.01 | X439: =(U439-V439)/U439 -> 0.12762074 | Y439: UPI | Z439: Not Returned | AA439: Online | AB439: 0.38680556 | AC439: =IF(HOUR(AB439)>=6,IF(HOUR(AB439)<12,"Morning",IF(HOUR(AB439)<17,"Afternoon",IF(HOUR(AB439)<21,"Evening","Night"))),"Night") -> Morning | AD439: Weekday
... A505: INV101995 | B505: 46109 | C505: CUST0106 | D505: Sangeetha Sekar | E505: Gold | F505: PRD007 | G505: Britannia Buns 2kg v2 | H505: Bakery | I505: STR161 | J505: FreshMart Jaipur Hub | K505: North | L505: 4933324 | M505: 0.00068394048 | N505: EMP0126 | O505: Anjali Kumar | P505: Sales | Q505: 6 | R505: 489 | S505: 0 | T505: 0 | U505: 3374.1 | V505: 1592.64 | W505: 1781.46 | X505: =(U505-V505)/U505 -> 0.52798079 | Y505: Debit Card | Z505: Not Returned | AA505: In-Store | AB505: 0.85 | AC505: =IF(HOUR(AB505)>=6,IF(HOUR(AB505)<12,"Morning",IF(HOUR(AB505)<17,"Afternoon",IF(HOUR(AB505)<21,"Evening","Night"))),"Night") -> Evening | AD505: Weekend
A506: INV101994 | B506: 45779 | C506: CUST0016 | D506: Vani Pandian | E506: Bronze | F506: PRD087 | G506: Organic Fresh Fresh Fruits Combo | H506: Fruits | I506: STR079 | J506: FreshMart Erode Hub | K506: South | L506: 2101567 | M506: 0 | N506: EMP0295 | O506: Lakshmi Nair | P506: Inventory | Q506: 2 | R506: 71.29 | S506: 5 | T506: 7.13 | U506: =Q506*R506-T506 -> 135.45 | V506: 118.74 | W506: 16.71 | X506: =(U506-V506)/U506 -> 0.12336656 | Y506: Wallet | Z506: Not Returned | AA506: In-Store | AB506: 0.39027778 | AC506: =IF(HOUR(AB506)>=6,IF(HOUR(AB506)<12,"Morning",IF(HOUR(AB506)<17,"Afternoon",IF(HOUR(AB506)<21,"Evening","Night"))),"Night") -> Morning | AD506: Weekday
A507: INV101993 | B507: 45767 | C507: CUST0394 | D507: Sudha Mudaliar | E507: Gold | F507: PRD019 | G507: Amul Paneer 1kg | H507: Dairy | I507: STR007 | J507: FreshMart Mysuru Towers | K507: South | L507: 988505 | M507: 0.0022257652 | N507: EMP0288 | O507: Chitra Selvam | P507: Sales | Q507: 4 | R507: 478.3 | S507: 0 | T507: 0 | U507: 2200.18 | V507: 1520.32 | W507: 679.86 | X507: =(U507-V507)/U507 -> 0.30900199 | Y507: Net Banking | Z507: Not Returned | AA507: In-Store | AB507: 0.75 | AC507: =IF(HOUR(AB507)>=6,IF(HOUR(AB507)<12,"Morning",IF(HOUR(AB507)<17,"Afternoon",IF(HOUR(AB507)<21,"Evening","Night"))),"Night") -> Evening | AD507: Weekend
A508: INV101992 | B508: 45884 | C508: CUST0671 | D508: Nagarajan Raj | E508: Gold | F508: PRD030 | G508: Nescafe Tea Combo | H508: Beverages | I508: STR130 | J508: FreshMart Surat Central | K508: West | L508: 969110 | M508: 0.00065366161 | N508: EMP0217 | O508: Radha Pillai | P508: Sales | Q508: 4 | R508: 197.96 | S508: 20 | T508: 158.37 | U508: 633.47 | V508: 568 | W508: 65.47 | X508: =(U508-V508)/U508 -> 0.10335138 | Y508: Wallet | Z508: Not Returned | AA508: Online | AB508: 0.42152778 | AC508: =IF(HOUR(AB508)>=6,IF(HOUR(AB508)<12,"Morning",IF(HOUR(AB508)<17,"Afternoon",IF(HOUR(AB508)<21,"Evening","Night"))),"Night") -> Morning | AD508: Weekday
A509: INV101991 | B509: 46109 | C509: CUST0572 | D509: Chandrasekar Balan | E509: Gold | F509: PRD023 | G509: Amul Butter 1L | H509: Dairy | I509: STR118 | J509: FreshMart Surat Heights | K509: West | L509: 2120932 | M509: 0.00125798 | N509: EMP0223 | O509: Kalpana Varma | P509: HR | Q509: 6 | R509: 386.68 | S509: 0 | T509: 0 | U509: 2668.09 | V509: 1596.6 | W509: 1071.49 | X509: =(U509-V509)/U509 -> 0.4015944 | Y509: Net Banking | Z509: Not Returned | AA509: In-Store | AB509: 0.39583333 | AC509: =IF(HOUR(AB509)>=6,IF(HOUR(AB509)<12,"Morning",IF(HOUR(AB509)<17,"Afternoon",IF(HOUR(AB509)<21,"Evening","Night"))),"Night") -> Morning | AD509: Weekend
A510: INV101990 | B510: 45984 | C510: CUST0586 | D510: Meena Selvam | E510: Bronze | F510: PRD134 | G510: Aachi Powdered Spices 200g v2 | H510: Masala | I510: STR012 | J510: FreshMart Chennai Junction | K510: South | L510: 544019 | M510: 0.0017911507 | N510: EMP0157 | O510: Elango Velan | P510: Cashier | Q510: 3 | R510: 353.05 | S510: 20 | T510: 211.83 | U510: 974.42 | V510: 788.4 | W510: 186.02 | X510: =(U510-V510)/U510 -> 0.19090331 | Y510: Debit Card | Z510: Not Returned | AA510: Mobile App | AB510: 0.60833333 | AC510: =IF(HOUR(AB510)>=6,IF(HOUR(AB510)<12,"Morning",IF(HOUR(AB510)<17,"Afternoon",IF(HOUR(AB510)<21,"Evening","Night"))),"Night") -> Afternoon | AD510: Weekend
A511: INV101989 | B511: 45793 | C511: CUST0641 | D511: Charulatha Raj | E511: Silver | F511: PRD126 | G511: Fortune Gingelly Oil 1L | H511: Oil | I511: STR067 | J511: FreshMart Salem Complex | K511: South | L511: 4677332 | M511: 0.00030831252 | N511: EMP0247 | O511: Sudha Balan | P511: Sales | Q511: 4 | R511: 360.52 | S511: 0 | T511: 0 | U511: 1442.08 | V511: 1297.92 | W511: 144.16 | X511: =(U511-V511)/U511 -> 0.099966715 | Y511: Wallet | Z511: Not Returned | AA511: In-Store | AB511: 0.86944444 | AC511: =IF(HOUR(AB511)>=6,IF(HOUR(AB511)<12,"Morning",IF(HOUR(AB511)<17,"Afternoon",IF(HOUR(AB511)<21,"Evening","Night"))),"Night") -> Evening | AD511: Weekday
A512: INV101988 | B512: 45931 | C512: CUST0553 | D512: Rajesh Varma | E512: Gold | F512: PRD048 | G512: Lays Chocolates 1kg | H512: Snacks | I512: STR157 | J512: FreshMart Lucknow Extension | K512: North | L512: 562953 | M512: 0.00076759516 | N512: EMP0122 | O512: Rajesh Chettiar | P512: Cashier | Q512: 3 | R512: 169.46 | S512: 15 | T512: 76.26 | U512: 432.12 | V512: 327.63 | W512: 104.49 | X512: =(U512-V512)/U512 -> 0.24180783 | Y512: Debit Card | Z512: Not Returned | AA512: Online | AB512: 0.75347222 | AC512: =IF(HOUR(AB512)>=6,IF(HOUR(AB512)<12,"Morning",IF(HOUR(AB512)<17,"Afternoon",IF(HOUR(AB512)<21,"Evening","Night"))),"Night") -> Evening | AD512: Weekday
A513: INV101987 | B513: 45823 | C513: CUST0290 | D513: Uma Pillai | E513: Bronze | F513: PRD110 | G513: India Gate Ponni Rice 1kg | H513: Rice | I513: STR113 | J513: FreshMart Pune Heights | K513: West | L513: 4088351 | M513: 0.00029561796 | N513: EMP0339 | O513: Hariharan Mudaliar | P513: Cashier | Q513: 4 | R513: 291.93 | S513: 10 | T513: 116.77 | U513: 1208.59 | V513: 1014.8 | W513: 193.79 | X513: =(U513-V513)/U513 -> 0.16034387 | Y513: UPI | Z513: Not Returned | AA513: In-Store | AB513: 0.43819444 | AC513: =IF(HOUR(AB513)>=6,IF(HOUR(AB513)<12,"Morning",IF(HOUR(AB513)<17,"Afternoon",IF(HOUR(AB513)<21,"Evening","Night"))),"Night") -> Morning | AD513: Weekend
A514: INV101986 | B514: 45928 | C514: CUST0270 | D514: Banu Venkataraman | E514: Gold | F514: PRD031 | G514: Nescafe Coffee Pack | H514: Beverages | I514: STR086 | J514: FreshMart Bengaluru Circle | K514: South | L514: 926537 | M514: 0.0016447158 | N514: EMP0263 | O514: Vani Nair | P514: Cashier | Q514: 4 | R514: 389.74 | S514: 15 | T514: 233.84 | U514: 1523.89 | V514: 1087.12 | W514: 436.77 | X514: =(U514-V514)/U514 -> 0.28661518 | Y514: Net Banking | Z514: Not Returned | AA514: In-Store | AB514: 0.82847222 | AC514: =IF(HOUR(AB514)>=6,IF(HOUR(AB514)<12,"Morning",IF(HOUR(AB514)<17,"Afternoon",IF(HOUR(AB514)<21,"Evening","Night"))),"Night") -> Evening | AD514: Weekend
A515: INV101985 | B515: 45774 | C515: CUST0039 | D515: Anjali Krishnan | E515: Silver | F515: PRD083 | G515: Organic Fresh Fresh Fruits 2kg | H515: Fruits | I515: STR118 | J515: FreshMart Surat Heights | K515: West | L515: 2120932 | M515: 0.00065811634 | N515: EMP0223 | O515: Kalpana Varma | P515: HR | Q515: 3 | R515: 425.88 | S515: 5 | T515: 63.88 | U515: 1395.82 | V515: 1072.41 | W515: 323.41 | X515: =(U515-V515)/U515 -> 0.23169893 | Y515: Cash | Z515: Not Returned | AA515: In-Store | AB515: 0.86388889 | AC515: =IF(HOUR(AB515)>=6,IF(HOUR(AB515)<12,"Morning",IF(HOUR(AB515)<17,"Afternoon",IF(HOUR(AB515)<21,"Evening","Night"))),"Night") -> Evening | AD515: Weekend
A516: INV101984 | B516: 45934 | C516: CUST0117 | D516: Raghav Menon | E516: Bronze | F516: PRD018 | G516: Aavin Cheese 200g | H516: Dairy | I516: STR125 | J516: FreshMart Nagpur Arcade | K516: West | L516: 1069200 | M516: 0.00080050505 | N516: EMP0133 | O516: Deepak Naicker | P516: Sales | Q516: 4 | R516: 232.58 | S516: 20 | T516: 186.06 | U516: 855.9 | V516: 764.8 | W516: 91.1 | X516: =(U516-V516)/U516 -> 0.10643767 | Y516: Debit Card | Z516: Not Returned | AA516: Mobile App | AB516: 0.40277778 | AC516: =IF(HOUR(AB516)>=6,IF(HOUR(AB516)<12,"Morning",IF(HOUR(AB516)<17,"Afternoon",IF(HOUR(AB516)<21,"Evening","Night"))),"Night") -> Morning | AD516: Weekend
A517: INV101983 | B517: 46005 | C517: CUST0494 | D517: Bhavani Reddy | E517: Gold | F517: PRD002 | G517: Britannia Buns Pack | H517: Bakery | I517: STR046 | J517: FreshMart Mysuru Colony | K517: South | L517: 808240 | M517: 0.0027943556 | N517: EMP0172 | O517: Geetha Naicker | P517: Cashier | Q517: 4 | R517: 490.98 | S517: 0 | T517: 0 | U517: 2258.51 | V517: 1016.2 | W517: 1242.31 | X517: =(U517-V517)/U517 -> 0.55005734 | Y517: Debit Card | Z517: Not Returned | AA517: Online | AB517: 0.84652778 | AC517: =IF(HOUR(AB517)>=6,IF(HOUR(AB517)<12,"Morning",IF(HOUR(AB517)<17,"Afternoon",IF(HOUR(AB517)<21,"Evening","Night"))),"Night") -> Evening | AD517: Weekend
A518: INV101982 | B518: 45757 | C518: CUST0249 | D518: Dhanush Menon | E518: Bronze | F518: PRD142 | G518: Lizol Dishwash 200g | H518: Cleaning | I518: STR137 | J518: FreshMart Ahmedabad Square | K518: West | L518: 4200752 | M518: 0.00033601365 | N518: EMP0039 | O518: Indira Menon | P518: Store Manager | Q518: 3 | R518: 522.78 | S518: 10 | T518: 156.83 | U518: 1411.51 | V518: 1187.61 | W518: 223.9 | X518: =(U518-V518)/U518 -> 0.15862445 | Y518: Net Banking | Z518: Returned | AA518: In-Store | AB518: 0.40138889 | AC518: =IF(HOUR(AB518)>=6,IF(HOUR(AB518)<12,"Morning",IF(HOUR(AB518)<17,"Afternoon",IF(HOUR(AB518)<21,"Evening","Night"))),"Night") -> Morning | AD518: Weekday
... A531: INV101969 | B531: 46103 | C531: CUST0324 | D531: Tamil Velan | E531: Gold | F531: PRD084 | G531: Local Farm Fresh Fruits Combo | H531: Fruits | I531: STR014 | J531: FreshMart Coimbatore Circle | K531: South | L531: 2118448 | M531: 0.00092950594 | N531: EMP0109 | O531: Dinesh Chettiar | P531: Store Manager | Q531: 7 | R531: 244.61 | S531: 0 | T531: 0 | U531: 1969.11 | V531: 1275.19 | W531: 693.92 | X531: =(U531-V531)/U531 -> 0.35240286 | Y531: Debit Card | Z531: Not Returned | AA531: In-Store | AB531: 0.41666667 | AC531: =IF(HOUR(AB531)>=6,IF(HOUR(AB531)<12,"Morning",IF(HOUR(AB531)<17,"Afternoon",IF(HOUR(AB531)<21,"Evening","Night"))),"Night") -> Morning | AD531: Weekend
A532: INV101968 | B532: 45899 | C532: CUST0275 | D532: Latha Nathan | E532: Gold | F532: PRD017 | G532: Nestle Curd 1kg | H532: Dairy | I532: STR075 | J532: FreshMart Salem Main Road | K532: South | L532: 838760 | M532: 0 | N532: EMP0033 | O532: Geetha Subramaniam | P532: Sales | Q532: 4 | R532: 522.43 | S532: 15 | T532: 313.46 | U532: =Q532*R532-T532 -> 1776.26 | V532: 1590.76 | W532: 451.94 | X532: =(U532-V532)/U532 -> 0.10443291 | Y532: Net Banking | Z532: Not Returned | AA532: Mobile App | AB532: 0.64305556 | AC532: =IF(HOUR(AB532)>=6,IF(HOUR(AB532)<12,"Morning",IF(HOUR(AB532)<17,"Afternoon",IF(HOUR(AB532)<21,"Evening","Night"))),"Night") -> Afternoon | AD532: Weekend
A533: INV101967 | B533: 45773 | C533: CUST0461 | D533: Prakash Achari | E533: Gold | F533: PRD067 | G533: Dove Shampoo 500g | H533: Personal Care | I533: STR159 | J533: FreshMart Jaipur Market | K533: North | L533: 2549253 | M533: 0.00037924443 | N533: EMP0335 | O533: Anjali Nair | P533: Sales | Q533: 5 | R533: 197.81 | S533: 15 | T533: 148.36 | U533: 966.79 | V533: 678.3 | W533: 288.49 | X533: =(U533-V533)/U533 -> 0.29839986 | Y533: Cash | Z533: Not Returned | AA533: In-Store | AB533: 0.72222222 | AC533: =IF(HOUR(AB533)>=6,IF(HOUR(AB533)<12,"Morning",IF(HOUR(AB533)<17,"Afternoon",IF(HOUR(AB533)<21,"Evening","Night"))),"Night") -> Evening | AD533: Weekend
A534: INV101966 | B534: 46026 | C534: CUST0244 | D534: Padma Naicker | E534: Silver | F534: PRD129 | G534: Everest Powdered Spices Combo | H534: Masala | I534: STR034 | J534: FreshMart Tiruppur Circle | K534: South | L534: 924804 | M534: 0.0018287767 | N534: EMP0059 | O534: Ezhil Rao | P534: Billing | Q534: 3 | R534: 490.22 | S534: 0 | T534: 0 | U534: 1691.26 | V534: 1120.74 | W534: 570.52 | X534: =(U534-V534)/U534 -> 0.3373343 | Y534: Cash | Z534: Not Returned | AA534: In-Store | AB534: 0.75347222 | AC534: =IF(HOUR(AB534)>=6,IF(HOUR(AB534)<12,"Morning",IF(HOUR(AB534)<17,"Afternoon",IF(HOUR(AB534)<21,"Evening","Night"))),"Night") -> Evening | AD534: Weekend
A535: INV101965 | B535: 46026 | C535: CUST0338 | D535: Mala Pillai | E535: Bronze | F535: PRD022 | G535: Aavin Milk Pack | H535: Dairy | I535: STR068 | J535: FreshMart Coimbatore Main Road | K535: South | L535: 456496 | M535: 0.0028519198 | N535: EMP0304 | O535: Deepa Menon | P535: Billing | Q535: 3 | R535: 397.22 | S535: 5 | T535: 59.58 | U535: 1301.89 | V535: 958.11 | W535: 343.78 | X535: =(U535-V535)/U535 -> 0.26406225 | Y535: Debit Card | Z535: Not Returned | AA535: In-Store | AB535: 0.54930556 | AC535: =IF(HOUR(AB535)>=6,IF(HOUR(AB535)<12,"Morning",IF(HOUR(AB535)<17,"Afternoon",IF(HOUR(AB535)<21,"Evening","Night"))),"Night") -> Afternoon | AD535: Weekend
A536: INV101964 | B536: 45991 | C536: CUST0427 | D536: Ashok Gounder | E536: Bronze | F536: PRD097 | G536: Local Farm Fresh Vegetables 250ml v2 | H536: Vegetables | I536: STR062 | J536: FreshMart Hyderabad Crossing | K536: South | L536: 789602 | M536: 0.0018119888 | N536: EMP0350 | O536: Uma Pandian | P536: Cashier | Q536: 4 | R536: 365.92 | S536: 15 | T536: 219.55 | U536: 1430.75 | V536: 1241.52 | W536: 189.23 | X536: =(U536-V536)/U536 -> 0.1322593 | Y536: Wallet | Z536: Not Returned | AA536: In-Store | AB536: 0.80277778 | AC536: =IF(HOUR(AB536)>=6,IF(HOUR(AB536)<12,"Morning",IF(HOUR(AB536)<17,"Afternoon",IF(HOUR(AB536)<21,"Evening","Night"))),"Night") -> Evening | AD536: Weekend
A537: INV101963 | B537: 45983 | C537: CUST0571 | D537: Nirmala Iyer | E537: Gold | F537: PRD130 | G537: Aachi Whole Spices 200g | H537: Masala | I537: STR078 | J537: FreshMart Tiruppur Towers | K537: South | L537: 496445 | M537: 0.0067509795 | N537: EMP0296 | O537: Vani Venkataraman | P537: Billing | Q537: 6 | R537: 571.44 | S537: 15 | T537: 514.3 | U537: 3351.49 | V537: 2387.52 | W537: 963.97 | X537: =(U537-V537)/U537 -> 0.28762431 | Y537: Wallet | Z537: Not Returned | AA537: Mobile App | AB537: 0.89513889 | AC537: =IF(HOUR(AB537)>=6,IF(HOUR(AB537)<12,"Morning",IF(HOUR(AB537)<17,"Afternoon",IF(HOUR(AB537)<21,"Evening","Night"))),"Night") -> Night | AD537: Weekend
A538: INV101962 | B538: 46111 | C538: CUST0354 | D538: Hemalatha Gounder | E538: Silver | F538: PRD056 | G538: Cadbury Namkeen Combo | H538: Snacks | I538: STR178 | J538: FreshMart Bhubaneswar Complex | K538: East | L538: 817593 | M538: 0.002039768 | N538: EMP0306 | O538: Yogesh Menon | P538: Cashier | Q538: 5 | R538: 333.54 | S538: 0 | T538: 0 | U538: 1667.7 | V538: 1192.15 | W538: 475.55 | X538: =(U538-V538)/U538 -> 0.28515321 | Y538: UPI | Z538: Not Returned | AA538: In-Store | AB538: 0.57638889 | AC538: =IF(HOUR(AB538)>=6,IF(HOUR(AB538)<12,"Morning",IF(HOUR(AB538)<17,"Afternoon",IF(HOUR(AB538)<21,"Evening","Night"))),"Night") -> Afternoon | AD538: Weekday
A539: INV101961 | B539: 46089 | C539: CUST0263 | D539: Deepa Kumar | E539: Gold | F539: PRD085 | G539: Local Farm Fresh Fruits 1kg | H539: Fruits | I539: STR028 | J539: FreshMart Ahmedabad Hub | K539: South | L539: 489039 | M539: 0.0053849897 | N539: EMP0123 | O539: Sundar Sharma | P539: Cashier | Q539: 6 | R539: 401.75 | S539: 5 | T539: 120.53 | U539: 2633.47 | V539: 2016.42 | W539: 617.05 | X539: =(U539-V539)/U539 -> 0.23431062 | Y539: Wallet | Z539: Not Returned | AA539: In-Store | AB539: 0.65486111 | AC539: =IF(HOUR(AB539)>=6,IF(HOUR(AB539)<12,"Morning",IF(HOUR(AB539)<17,"Afternoon",IF(HOUR(AB539)<21,"Evening","Night"))),"Night") -> Afternoon | AD539: Weekend
A540: INV101960 | B540: 45808 | C540: CUST0356 | D540: Janani Chettiar | E540: Bronze | F540: PRD053 | G540: Cadbury Namkeen Pack | H540: Snacks | I540: STR092 | J540: FreshMart Chennai Gardens | K540: South | L540: 1922335 | M540: 0.00013361355 | N540: EMP0336 | O540: Sanjay Sharma | P540: Billing | Q540: 1 | R540: 262.77 | S540: 15 | T540: 39.42 | U540: 256.85 | V540: 194.64 | W540: 62.21 | X540: =(U540-V540)/U540 -> 0.24220362 | Y540: Net Banking | Z540: Not Returned | AA540: In-Store | AB540: 0.90972222 | AC540: =IF(HOUR(AB540)>=6,IF(HOUR(AB540)<12,"Morning",IF(HOUR(AB540)<17,"Afternoon",IF(HOUR(AB540)<21,"Evening","Night"))),"Night") -> Night | AD540: Weekend
A541: INV101959 | B541: 45931 | C541: CUST0613 | D541: Meena Menon | E541: Gold | F541: PRD028 | G541: Tata Tea Soft Drinks 500g | H541: Beverages | I541: STR057 | J541: FreshMart Madurai Point | K541: South | L541: 2213986 | M541: 0.0011612585 | N541: EMP0065 | O541: Kavya Velan | P541: Cashier | Q541: 8 | R541: 401.72 | S541: 20 | T541: 642.75 | U541: 2571.01 | V541: 2479.84 | W541: 91.17 | X541: =(U541-V541)/U541 -> 0.035460772 | Y541: Net Banking | Z541: Not Returned | AA541: Online | AB541: 0.78541667 | AC541: =IF(HOUR(AB541)>=6,IF(HOUR(AB541)<12,"Morning",IF(HOUR(AB541)<17,"Afternoon",IF(HOUR(AB541)<21,"Evening","Night"))),"Night") -> Evening | AD541: Weekday
A542: INV101958 | B542: 45926 | C542: CUST0590 | D542: Kavya Reddy | E542: Silver | F542: PRD085 | G542: Local Farm Fresh Fruits 1kg | H542: Fruits | I542: STR033 | J542: FreshMart Ahmedabad Complex | K542: South | L542: 1058381 | M542: 0.0011043566 | N542: EMP0113 | O542: Radha Rao | P542: Inventory | Q542: 3 | R542: 389.61 | S542: 0 | T542: 0 | U542: 1168.83 | V542: 1008.21 | W542: 160.62 | X542: =(U542-V542)/U542 -> 0.13741947 | Y542: Cash | Z542: Not Returned | AA542: In-Store | AB542: 0.64236111 | AC542: =IF(HOUR(AB542)>=6,IF(HOUR(AB542)<12,"Morning",IF(HOUR(AB542)<17,"Afternoon",IF(HOUR(AB542)<21,"Evening","Night"))),"Night") -> Afternoon | AD542: Weekday
A543: INV101957 | B543: 45939 | C543: CUST0158 | D543: Hemalatha Murugan | E543: Bronze | F543: PRD078 | G543: Vim Kitchenware Combo | H543: Household | I543: STR123 | J543: FreshMart Mumbai Extension | K543: West | L543: 520137 | M543: 0.0010056966 | N543: EMP0299 | O543: Nandhini Kumar | P543: Cashier | Q543: 2 | R543: 261.55 | S543: 0 | T543: 0 | U543: 523.1 | V543: 430.06 | W543: 93.04 | X543: =(U543-V543)/U543 -> 0.17786274 | Y543: UPI | Z543: Not Returned | AA543: In-Store | AB543: 0.58263889 | AC543: =IF(HOUR(AB543)>=6,IF(HOUR(AB543)<12,"Morning",IF(HOUR(AB543)<17,"Afternoon",IF(HOUR(AB543)<21,"Evening","Night"))),"Night") -> Afternoon | AD543: Weekday
A544: INV101956 | B544: 46067 | C544: CUST0174 | D544: Yogesh Sharma | E544: Silver | F544: PRD098 | G544: Organic Fresh Fresh Vegetables 250ml | H544: Vegetables | I544: STR060 | J544: FreshMart Erode Square | K544: North | L544: 2220333 | M544: 8.1807549e-05 | N544: EMP0140 | O544: Kavya Sharma | P544: Sales | Q544: 2 | R544: 83.13 | S544: 5 | T544: 8.31 | U544: 181.64 | V544: 138.18 | W544: 43.46 | X544: =(U544-V544)/U544 -> 0.23926448 | Y544: Net Banking | Z544: Not Returned | AA544: In-Store | AB544: 0.44652778 | AC544: =IF(HOUR(AB544)>=6,IF(HOUR(AB544)<12,"Morning",IF(HOUR(AB544)<17,"Afternoon",IF(HOUR(AB544)<21,"Evening","Night"))),"Night") -> Morning | AD544: Weekend
... A638: INV101863 | B638: 45837 | C638: CUST0654 | D638: Gokul Sekar | E638: Gold | F638: PRD055 | G638: Cadbury Biscuits Pack | H638: Snacks | I638: STR058 | J638: FreshMart Erode Central | K638: South | L638: 983222 | M638: 0.0005998035 | N638: EMP0133 | O638: Deepak Naicker | P638: Sales | Q638: 4 | R638: 142.45 | S638: 10 | T638: 56.98 | U638: 589.74 | V638: 382.8 | W638: 206.94 | X638: =(U638-V638)/U638 -> 0.3509004 | Y638: Debit Card | Z638: Not Returned | AA638: Online | AB638: 0.53194444 | AC638: =IF(HOUR(AB638)>=6,IF(HOUR(AB638)<12,"Morning",IF(HOUR(AB638)<17,"Afternoon",IF(HOUR(AB638)<21,"Evening","Night"))),"Night") -> Afternoon | AD638: Weekend
A639: INV101862 | B639: 45858 | C639: CUST0046 | D639: Kishore Murugan | E639: Gold | F639: PRD054 | G639: Lays Namkeen 2kg | H639: Snacks | I639: STR099 | J639: FreshMart Nagpur Plaza | K639: West | L639: 572932 | M639: 0 | N639: EMP0026 | O639: Nandhini Pandian | P639: Operations | Q639: 7 | R639: 548.45 | S639: 15 | T639: 575.87 | U639: =Q639*R639-T639 -> 3263.28 | V639: 2654.33 | W639: 1098.44 | X639: =(U639-V639)/U639 -> 0.18660673 | Y639: Credit Card | Z639: Not Returned | AA639: In-Store | AB639: 0.86458333 | AC639: =IF(HOUR(AB639)>=6,IF(HOUR(AB639)<12,"Morning",IF(HOUR(AB639)<17,"Afternoon",IF(HOUR(AB639)<21,"Evening","Night"))),"Night") -> Evening | AD639: Weekend
A640: INV101861 | B640: 45788 | C640: CUST0587 | D640: Uma Iyer | E640: Bronze | F640: PRD035 | G640: Coca-Cola Coffee 500g | H640: Beverages | I640: STR006 | J640: FreshMart Mysuru Junction | K640: South | L640: 2561982 | M640: 0.00045188842 | N640: EMP0265 | O640: Padma Subramaniam | P640: Operations | Q640: 2 | R640: 503.36 | S640: 0 | T640: 0 | U640: 1157.73 | V640: 779.6 | W640: 378.13 | X640: =(U640-V640)/U640 -> 0.32661329 | Y640: Wallet | Z640: Not Returned | AA640: Online | AB640: 0.51458333 | AC640: =IF(HOUR(AB640)>=6,IF(HOUR(AB640)<12,"Morning",IF(HOUR(AB640)<17,"Afternoon",IF(HOUR(AB640)<21,"Evening","Night"))),"Night") -> Afternoon | AD640: Weekend
...

Sheet Calculations
A2: TOTAL SALES | C2: CURRENT MONTHLY AVG(SALES) | E2: CURRENT MONTHLY AVG(PROFIT) | G2: CURRENT MONTHLY AVG(AVG ORDER VAL)
A3: =SUM(Table14__2_1[Sales_Amount]) -> 2892988.6 | C3: =AVERAGE('Sales Sheet'!U4:U2500) -> 1157.267 | E3: =AVERAGE('Sales Sheet'!W4:W2500) -> 294.84325 | G3: =SUM('Sales Sheet'!U4:U2500)/COUNTA('Sales Sheet'!AB4:AB2500) -> 1157.267
A5: TOTAL PROFIT | C5: PREVIOUS MONTHLY AVG(SALES) | E5: PREVIOUS MONTHLY AVG(PROFIT) | G5: PREVIOUS MONTHLY AVG(AVG ORDER VAL)
A6: =SUM(Table14__2_1[Profit]) -> 737358.89 | C6: =AVERAGE(Table14__2_1[Sales_Amount]) -> 1157.1954 | E6: =AVERAGE(Table14__2_1[Profit]) -> 294.94356 | G6: =SUM(Table14__2_1[Sales_Amount])/COUNTA(Table14__2_1[Order_Time]) -> 1157.1954
A8: AVG ORDER VALUE | C8: SALES GROWTH | E8: PROFIT GROWTH | G8: AVG ORDER VALUE GROWTH
A9: =A3/A12 -> 1157.1954 | C9: =((C3-C6)/C6) -> 6.1881041e-05 | E9: =((E3-E6)/E6) -> -0.00034009254 | G9: =((G3-G6)/G6) -> 6.1881041e-05
A11: TOTAL ORDERS | C11: =IF(Calculations!C9>=0,"▲ "&TEXT(Calculations!C9,"0.00%")&" vs Last Year","▼ "&TEXT(Calculations!C9,"0.00%")&" vs Last Year") -> ▲ 0.01% vs Last Year | E11: =IF(Calculations!E9>=0,"▲ "&TEXT(Calculations!E9,"0.00%")&" vs Last Year","▼ "&TEXT(Calculations!E9,"0.00%")&" vs Last Year") -> ▼ -0.03% vs Last Year | G11: =IF(Calculations!G9>=0,"▲ "&TEXT(Calculations!G9,"0.00%")&" vs Last Year","▼ "&TEXT(Calculations!G9,"0.00%")&" vs Last Year") -> ▲ 0.01% vs Last Year
A12: =COUNTA(Table14__2_1[Order_Time]) -> 2500
A14: TOTAL CUSTOMERS | C14: =IF(Calculations!C9>=0,"▲ "&TEXT(Calculations!C9,"0.00%")&" vs Last Year","▼ "&TEXT(ABS(Calculations!C9),"0.00%")&" vs Last Year") -> ▲ 0.01% vs Last Year
A15: =COUNTA((Table10[Customer_ID])) -> 700
C16: ▲ | E16: ▼ | G16: Sum of Sales_Amount
A17: TOTAL QUANTITY | G17: 2868432.6
A18: =SUM(Table14__2_1[Quantity]) -> 9823
A20: TOTAL COST | C20: Count of Order_Time | E20: Sum of Cost_Amount | G20: Sum of Profit
A21: =SUM(Table14__2_1[Cost_Amount]) -> 2155163 | C21: 2500 | E21: 2155163 | G21: 737358.89
A24: PROFIT MARGIN % | E24: Sum of Quantity
A25: =G21/G17 -> 0.25705986 | E25: 9823

Sheet Detail1
A1: Details for Margins % - Catogory: Household
A3: Invoice_Number | B3: Transaction_Date | C3: Customer_ID | D3: Customer Name | E3: Membership | F3: Product_ID | G3: Product Name | H3: Catogory | I3: Store_ID | J3: Store Name | K3: Region | L3: Target | M3: Acheivements | N3: Employee_ID | O3: Employee Name | P3: Department | Q3: Quantity | R3: Unit_Price | S3: Discount_Pct | T3: Discount_Amount | U3: Sales_Amount | V3: Cost_Amount | W3: Profit | X3: Margin % | Y3: Payment_Mode | Z3: Return_Status | AA3: Sales_Channel | AB3: Order_Time | AC3: Time Category | AD3: Day_Type
A4: INV102406 | B4: 45857 | C4: CUST0512 | D4: Elango Rao | E4: Silver | F4: PRD073 | G4: Harvest Gold Rusk 1kg | H4: Household | I4: STR084 | J4: FreshMart Tiruppur Market | K4: South | L4: 5001334 | M4: 0.00036116964 | N4: EMP0288 | O4: Chitra Selvam | P4: Sales | Q4: 5 | R4: 392.68 | S4: 20 | T4: 392.68 | U4: 1806.33 | V4: 1595.25 | W4: 211.08 | X4: 0.11685572 | Y4: Wallet | Z4: Not Returned | AA4: In-Store | AB4: 0.49930556 | AC4: Morning | AD4: Weekend
A5: INV102232 | B5: 45998 | C5: CUST0531 | D5: Kamala Sekar | E5: Silver | F5: PRD073 | G5: Harvest Gold Rusk 1kg | H5: Household | I5: STR121 | J5: FreshMart Pune Junction | K5: West | L5: 542771 | M5: 0.00066558457 | N5: EMP0123 | O5: Sundar Sharma | P5: Cashier | Q5: 1 | R5: 392.68 | S5: 20 | T5: 78.54 | U5: 361.26 | V5: 319.05 | W5: 42.21 | X5: 0.11684106 | Y5: Wallet | Z5: Not Returned | AA5: In-Store | AB5: 0.625 | AC5: Afternoon | AD5: Weekend
A6: INV101198 | B6: 46054 | C6: CUST0422 | D6: Balamurugan Naidu | E6: Silver | F6: PRD074 | G6: Surf Excel Tissue Combo | H6: Household | I6: STR024 | J6: FreshMart Bengaluru Plaza | K6: South | L6: 1059131 | M6: 0.00044983104 | N6: EMP0005 | O6: Harini Sekar | P6: Inventory | Q6: 1 | R6: 414.29 | S6: 0 | T6: 0 | U6: 476.43 | V6: 314.26 | W6: 162.17 | X6: 0.34038579 | Y6: Debit Card | Z6: Not Returned | AA6: In-Store | AB6: 0.84791667 | AC6: Evening | AD6: Weekend
A7: INV102201 | B7: 45795 | C7: CUST0267 | D7: Manoj Gounder | E7: Silver | F7: PRD080 | G7: Vim Kitchenware 1kg | H7: Household | I7: STR074 | J7: FreshMart Mysuru Main Road | K7: South | L7: 4458567 | M7: 0.00014222731 | N7: EMP0270 | O7: Priya Venkataraman | P7: Operations | Q7: 2 | R7: 275.71 | S7: 0 | T7: 0 | U7: 634.13 | V7: 412.6 | W7: 221.53 | X7: 0.34934477 | Y7: Wallet | Z7: Not Returned | AA7: In-Store | AB7: 0.85277778 | AC7: Evening | AD7: Weekend
A8: INV101812 | B8: 46073 | C8: CUST0530 | D8: Deepak Chettiar | E8: Silver | F8: PRD080 | G8: Vim Kitchenware 1kg | H8: Household | I8: STR009 | J8: FreshMart Kochi Square | K8: South | L8: 429599 | M8: 0.0021820582 | N8: EMP0317 | O8: Umesh Sharma | P8: HR | Q8: 4 | R8: 275.71 | S8: 15 | T8: 165.43 | U8: 937.41 | V8: 825.2 | W8: 112.21 | X8: 0.11970216 | Y8: Wallet | Z8: Not Returned | AA8: In-Store | AB8: 0.50347222 | AC8: Afternoon | AD8: Weekday
A9: INV101701 | B9: 45902 | C9: CUST0415 | D9: Bharath Devi | E9: Gold | F9: PRD076 | G9: Surf Excel Tissue Combo v2 | H9: Household | I9: STR061 | J9: FreshMart Hyderabad Colony | K9: South | L9: 2456631 | M9: 0.0010711743 | N9: EMP0329 | O9: Balamurugan Nair | P9: Cashier | Q9: 6 | R9: 438.58 | S9: 0 | T9: 0 | U9: 2631.48 | V9: 1921.14 | W9: 710.34 | X9: 0.26993935 | Y9: Wallet | Z9: Not Returned | AA9: Mobile App | AB9: 0.70833333 | AC9: Evening | AD9: Weekday
A10: INV101553 | B10: 45984 | C10: CUST0143 | D10: Charulatha Iyer | E10: Silver | F10: PRD070 | G10: Surf Excel Batteries 2kg | H10: Household | I10: STR128 | J10: FreshMart Surat Junction | K10: West | L10: 2138213 | M10: 0.0002134633 | N10: EMP0177 | O10: Raghav Iyer | P10: Store Manager | Q10: 2 | R10: 233.47 | S10: 15 | T10: 70.04 | U10: 456.43 | V10: 377.96 | W10: 78.47 | X10: 0.17192121 | Y10: Wallet | Z10: Not Returned | AA10: Mobile App | AB10: 0.87777778 | AC10: Night | AD10: Weekend
A11: INV101667 | B11: 46097 | C11: CUST0285 | D11: Aishwarya Gounder | E11: Silver | F11: PRD080 | G11: Vim Kitchenware 1kg | H11: Household | I11: STR123 | J11: FreshMart Mumbai Extension | K11: West | L11: 520137 | M11: 0.0021202875 | N11: EMP0133 | O11: Deepak Naicker | P11: Sales | Q11: 5 | R11: 275.71 | S11: 20 | T11: 275.71 | U11: 1102.84 | V11: 1031.5 | W11: 71.34 | X11: 0.064687534 | Y11: Wallet | Z11: Not Returned | AA11: Online | AB11: 0.52847222 | AC11: Afternoon | AD11: Weekday
A12: INV101495 | B12: 45941 | C12: CUST0158 | D12: Hemalatha Murugan | E12: Bronze | F12: PRD074 | G12: Surf Excel Tissue Combo | H12: Household | I12: STR076 | J12: FreshMart Hyderabad Towers | K12: South | L12: 1041021 | M12: 0.0012356811 | N12: EMP0056 | O12: Anjali Balan | P12: Sales | Q12: 3 | R12: 414.29 | S12: 10 | T12: 124.29 | U12: 1286.37 | V12: 942.78 | W12: 343.59 | X12: 0.26710045 | Y12: Wallet | Z12: Not Returned | AA12: In-Store | AB12: 0.75 | AC12: Evening | AD12: Weekend
A13: INV101446 | B13: 46005 | C13: CUST0638 | D13: Deepak Gounder | E13: Gold | F13: PRD081 | G13: Eveready Batteries 250ml | H13: Household | I13: STR008 | J13: FreshMart Kochi Plaza | K13: South | L13: 2481146 | M13: 0.00015504529 | N13: EMP0308 | O13: Thenmozhi Selvam | P13: Cashier | Q13: 7 | R13: 56.22 | S13: 15 | T13: 59.03 | U13: 384.69 | V13: 314.72 | W13: 69.97 | X13: 0.18188671 | Y13: Wallet | Z13: Not Returned | AA13: In-Store | AB13: 0.83541667 | AC13: Evening | AD13: Weekend
A14: INV101387 | B14: 45834 | C14: CUST0378 | D14: Radha Nair | E14: Gold | F14: PRD073 | G14: Harvest Gold Rusk 1kg | H14: Household | I14: STR161 | J14: FreshMart Jaipur Hub | K14: North | L14: 4933324 | M14: 0.00031846276 | N14: EMP0126 | O14: Anjali Kumar | P14: Sales | Q14: 4 | R14: 392.77 | S14: 0 | T14: 0 | U14: 1571.08 | V14: 1276.2 | W14: 294.88 | X14: 0.18769254 | Y14: Wallet | Z14: Not Returned | AA14: Online | AB14: 0.49861111 | AC14: Morning | AD14: Weekday
A15: INV101359 | B15: 46069 | C15: CUST0311 | D15: Sudha Pandian | E15: Bronze | F15: PRD076 | G15: Surf Excel Tissue Combo v2 | H15: Household | I15: STR095 | J15: FreshMart Ahmedabad Gardens | K15: West | L15: 1952402 | M15: 0.00040530587 | N15: EMP0177 | O15: Raghav Iyer | P15: Store Manager | Q15: 2 | R15: 395.66 | S15: 0 | T15: 0 | U15: 791.32 | V15: 640.38 | W15: 150.94 | X15: 0.19074458 | Y15: Wallet | Z15: Not Returned | AA15: Mobile App | AB15: 0.64236111 | AC15: Afternoon | AD15: Weekday
... A145: INV100950 | B145: 46093 | C145: CUST0263 | D145: Deepa Kumar | E145: Gold | F145: PRD073 | G145: Harvest Gold Rusk 1kg | H145: Household | I145: STR035 | J145: FreshMart Kochi Circle | K145: South | L145: 4405163 | M145: 0.00024680358 | N145: EMP0158 | O145: Kavya Varma | P145: Sales | Q145: 3 | R145: 402.67 | S145: 10 | T145: 120.8 | U145: 1087.21 | V145: 957.15 | W145: 130.06 | X145: 0.1196273 | Y145: Cash | Z145: Not Returned | AA145: Mobile App | AB145: 0.78680556 | AC145: Evening | AD145: Weekday

Sheet Dashboard
A1: FreshMart Profitability Leakage Analysis
D14: Category Performance | I14: Top 10 Products by Profits | M14: Target Vs Actual Sales (Store Performance)
D15: Row Labels | E15: Sales | F15: Profits | G15: Margins % | I15: Row Labels | J15: Sales | K15: Sum of Profit | M15: Row Labels | N15: Targets | O15: Sales | P15: Status & Achievement %
D16: Beverages | E16: 479332.71 | F16: 118799.11 | G16: 0.21515036 | I16: Harvest Gold Rusk 1kg | J16: 75156.97 | K16: 28902.89 | M16: STR086 | N16: 926537 | O16: 36723.73 | P16: =O16/N16 -> 0.039635471
D17: Bakery | E17: 358017.14 | F17: 149305.74 | G17: 0.38865334 | I17: Coca-Cola Coffee 500g | J17: 78629.02 | K17: 20159.02 | M17: STR059 | N17: 982441 | O17: 34742.58 | P17: =O17/N17 -> 0.035363528
D18: Dairy | E18: 351546.11 | F18: 74650.33 | G18: 0.18425272 | I18: Nescafe Coffee 1kg | J18: 68998.76 | K18: 19301.51 | M18: STR033 | N18: 1058381 | O18: 34391.99 | P18: =O18/N18 -> 0.032494905
D19: Snacks | E19: 287706.41 | F19: 84119.62 | G19: 0.26257943 | I19: Lays Namkeen 2kg | J19: 53010.1 | K19: 17706.3 | M19: STR018 | N19: 970105 | O19: 31485.48 | P19: =O19/N19 -> 0.032455744
D20: Fruits | E20: 235509.05 | F20: 46573.77 | G20: 0.16976024 | I20: Nescafe Soft Drinks Pack | J20: 62694.19 | K20: 16965.71 | M20: STR097 | N20: 2632479 | O20: 31447.34 | P20: =O20/N20 -> 0.011945903
D21: Vegetables | E21: 218513.72 | F21: 40777.23 | G21: 0.16945918 | I21: Nescafe Coffee Pack | J21: 56784.24 | K21: 13571.22 | M21: STR092 | N21: 1922335 | O21: 30207.06 | P21: =O21/N21 -> 0.015713734
D22: Personal Care | E22: 192624.16 | F22: 61117.96 | G22: 0.29057475 | I22: Nestle Curd 1kg | J22: 62189.96 | K22: 13328.34 | M22: STR056 | N22: 4116030 | O22: 29715.49 | P22: =O22/N22 -> 0.0072194542
D23: Rice | E23: 167384.1 | F23: 30185.16 | G23: 0.14821474 | I23: Pepsi Tea 200g | J23: 53709.63 | K23: 13245.28 | M23: STR036 | N23: 471467 | O23: 29122.22 | P23: =O23/N23 -> 0.061769371
D24: Masala | E24: 153158.06 | F24: 41220.14 | G24: 0.24638324 | I24: Tata Tea Soft Drinks 500g | J24: 53103.27 | K24: 11255.97 | M24: STR023 | N24: 4282083 | O24: 29035 | P24: =O24/N24 -> 0.0067805785
D25: Household | E25: 144591.68 | F25: 35467.75 | G25: 0.21385415 | I25: Local Farm Fresh Vegetables 200g | J25: 46278.18 | K25: 9037.92 | M25: STR080 | N25: 2169082 | O25: 28821.34 | P25: =O25/N25 -> 0.013287345
A26: 🎯 Recommendations
A28: 📈 Strengthen South Region
A29: 💰 Promote High-Margin Categories
A31: 🛍️ Grow Online Sales
A32: 🎯 Review Store Targets
A33: ⏰ Optimize Afternoon Promotions

Sheet Sheet2
K3: Row Labels | L3: Sum of Sales_Amount | M3: Sum of Profit
K4: 2025 | L4: 2335789.5 | M4: 602867.99
K5: Mar | L5: 1682.32 | M5: 252.44
K6: Apr | L6: 195249.44 | M6: 50155.37
K7: May | L7: 223829.24 | M7: 61161.92
K8: Jun | L8: 226577.54 | M8: 58096.27
K9: Jul | L9: 171047.56 | M9: 42067
K10: Aug | L10: 193434.23 | M10: 49379.88
K11: Sep | L11: 239642.24 | M11: 58943.03
K12: Oct | L12: 445171.86 | M12: 115133.04
K13: Nov | L13: 303499.88 | M13: 79014.61
K14: Dec | L14: 335655.2 | M14: 88664.43
K15: 2026 | L15: 532643.09 | M15: 134490.9
... K19: Grand Total | L19: 2868432.6 | M19: 737358.89
I24: Row Labels | J24: Sum of Sales_Amount
I25: East | J25: 62655.19
I26: North | J26: 246937.59
I27: South | J27: 1872387.9
I28: West | J28: 686451.93
I29: Grand Total | J29: 2868432.6
A37: Row Labels | B37: Sum of Sales_Amount
A38: STR086 | B38: 36723.73
A39: STR059 | B39: 34742.58
A40: STR033 | B40: 34391.99
A41: STR018 | B41: 31485.48
A42: STR097 | B42: 31447.34
A43: STR092 | B43: 30207.06
A44: STR056 | B44: 29715.49
A45: STR036 | B45: 29122.22
A46: STR023 | B46: 29035
A47: STR080 | B47: 28821.34
A48: Grand Total | B48: 315692.23
A53: Row Labels | B53: Average of Target | C53: Sum of Sales_Amount | D53: Status & Achievement %
A54: STR086 | B54: 926537 | C54: 36723.73 | D54: =C54/B54 -> 0.039635471
A55: STR059 | B55: 982441 | C55: 34742.58 | D55: =C55/B55 -> 0.035363528
A56: STR033 | B56: 1058381 | C56: 34391.99 | D56: =C56/B56 -> 0.032494905
A57: STR018 | B57: 970105 | C57: 31485.48 | D57: =C57/B57 -> 0.032455744
A58: STR097 | B58: 2632479 | C58: 31447.34 | D58: =C58/B58 -> 0.011945903
A59: STR092 | B59: 1922335 | C59: 30207.06 | D59: =C59/B59 -> 0.015713734
A60: STR056 | B60: 4116030 | C60: 29715.49 | D60: =C60/B60 -> 0.0072194542
A61: STR036 | B61: 471467 | C61: 29122.22 | D61: =C61/B61 -> 0.061769371
A62: STR023 | B62: 4282083 | C62: 29035 | D62: =C62/B62 -> 0.0067805785
A63: STR080 | B63: 2169082 | C63: 28821.34 | D63: =C63/B63 -> 0.013287345
A65: Row Labels | B65: Average of Margin %
A66: 0 | B66: 0.28039955
A67: 5 | B67: 0.23697923
A68: 10 | B68: 0.20188807
A69: 15 | B69: 0.161727
A70: 20 | B70: 0.10695531
A71: Grand Total | B71: 0.22229773
A74: Row Labels | B74: Sum of Sales_Amount
A75: Bronze | B75: 473586.24
A76: Gold | B76: 1717840.5
A77: Silver | B77: 677005.88
A78: Grand Total | B78: 2868432.6
A80: Row Labels | B80: Sum of Sales_Amount
A81: Not Returned | B81: 2733740.3
A82: Returned | B82: 134692.3
A83: Grand Total | B83: 2868432.6
A87: Row Labels | B87: Sum of Sales_Amount
A88: In-Store | B88: 1969380.3
A89: Mobile App | B89: 286557.95
A90: Online | B90: 612494.35
A91: Grand Total | B91: 2868432.6
A96: Row Labels | B96: Sum of Sales_Amount
A97: Cash | B97: 432694.8
A98: Credit Card | B98: 468798.76
A99: Debit Card | B99: 490398.19
A100: Net Banking | B100: 438113.87
A101: UPI | B101: 549309.6
A102: Wallet | B102: 489117.38
A103: Grand Total | B103: 2868432.6
A106: Row Labels | B106: Sum of Sales_Amount
A107: Afternoon | B107: 1087071.5
A108: Evening | B108: 937274.78
A109: Morning | B109: 661764.9
A110: Night | B110: 182321.37
A111: Grand Total | B111: 2868432.6
A116: Row Labels | B116: Sum of Sales_Amount | C116: Sum of Profit | D116: Sum of Margin %
A117: Beverages | B117: 479332.71 | C117: 118799.11 | D117: 82.617738
A118: Bakery | B118: 358017.14 | C118: 149305.74 | D118: 89.778921
A119: Dairy | B119: 351546.11 | C119: 74650.33 | D119: 59.145124
A120: Snacks | B120: 287706.41 | C120: 84119.62 | D120: 66.695175
A121: Fruits | B121: 235509.05 | C121: 46573.77 | D121: 31.914926
A122: Vegetables | B122: 218513.72 | C122: 40777.23 | D122: 33.722376
A123: Personal Care | B123: 192624.16 | C123: 61117.96 | D123: 44.457937
A124: Rice | B124: 167384.1 | C124: 30185.16 | D124: 25.93758
A125: Masala | B125: 153158.06 | C125: 41220.14 | D125: 32.768972
A126: Household | B126: 144591.68 | C126: 35467.75 | D126: 30.367289
